{
"meta":{"test_sets":[],"test_metrics":[],"learn_metrics":[{"best_value":"Min","name":"RMSE"}],"launch_mode":"Train","parameters":"","iteration_count":1000,"learn_sets":["learn"],"name":"experiment"},
"iterations":[
{"learn":[0.9426194829],"iteration":0,"passed_time":0.0791254493,"remaining_time":79.04632385},
{"learn":[0.936117207],"iteration":1,"passed_time":0.09342015772,"remaining_time":46.6166587},
{"learn":[0.9305430226],"iteration":2,"passed_time":0.1077451029,"remaining_time":35.80728921},
{"learn":[0.9256829551],"iteration":3,"passed_time":0.1218003314,"remaining_time":30.32828252},
{"learn":[0.9216963592],"iteration":4,"passed_time":0.1356199779,"remaining_time":26.9883756},
{"learn":[0.9183910244],"iteration":5,"passed_time":0.1545241163,"remaining_time":25.59949527},
{"learn":[0.9152778858],"iteration":6,"passed_time":0.1747221766,"remaining_time":24.78558876},
{"learn":[0.9125711133],"iteration":7,"passed_time":0.1893189025,"remaining_time":23.47554391},
{"learn":[0.9104938614],"iteration":8,"passed_time":0.2124838372,"remaining_time":23.39683141},
{"learn":[0.9084176002],"iteration":9,"passed_time":0.2245022393,"remaining_time":22.22572169},
{"learn":[0.9064407957],"iteration":10,"passed_time":0.2400348537,"remaining_time":21.58131548},
{"learn":[0.9049367255],"iteration":11,"passed_time":0.2691333119,"remaining_time":22.15864268},
{"learn":[0.9032670645],"iteration":12,"passed_time":0.2893486997,"remaining_time":21.96824359},
{"learn":[0.9019106581],"iteration":13,"passed_time":0.3108723503,"remaining_time":21.89429553},
{"learn":[0.9008240847],"iteration":14,"passed_time":0.3628888348,"remaining_time":23.82970015},
{"learn":[0.8997242978],"iteration":15,"passed_time":0.400826636,"remaining_time":24.65083811},
{"learn":[0.8986518603],"iteration":16,"passed_time":0.432394299,"remaining_time":25.00256447},
{"learn":[0.8976781786],"iteration":17,"passed_time":0.4448576057,"remaining_time":24.26945382},
{"learn":[0.8969312243],"iteration":18,"passed_time":0.4646853202,"remaining_time":23.99243679},
{"learn":[0.8961895108],"iteration":19,"passed_time":0.479654065,"remaining_time":23.50304919},
{"learn":[0.8954899923],"iteration":20,"passed_time":0.4932704693,"remaining_time":22.9957995},
{"learn":[0.8949250892],"iteration":21,"passed_time":0.5100118301,"remaining_time":22.67234408},
{"learn":[0.89442499],"iteration":22,"passed_time":0.530533318,"remaining_time":22.53613268},
{"learn":[0.8939572803],"iteration":23,"passed_time":0.5570937569,"remaining_time":22.65514612},
{"learn":[0.893217893],"iteration":24,"passed_time":0.5979463451,"remaining_time":23.31990746},
{"learn":[0.8926393287],"iteration":25,"passed_time":0.6261595958,"remaining_time":23.45690178},
{"learn":[0.8920392],"iteration":26,"passed_time":0.6403299757,"remaining_time":23.07559505},
{"learn":[0.8916100766],"iteration":27,"passed_time":0.6573263152,"remaining_time":22.81861351},
{"learn":[0.8911526068],"iteration":28,"passed_time":0.673656969,"remaining_time":22.55589368},
{"learn":[0.8905454076],"iteration":29,"passed_time":0.6943361228,"remaining_time":22.4502013},
{"learn":[0.890042659],"iteration":30,"passed_time":0.7105317629,"remaining_time":22.20984769},
{"learn":[0.8895849076],"iteration":31,"passed_time":0.729521232,"remaining_time":22.06801727},
{"learn":[0.8892763589],"iteration":32,"passed_time":0.7494924517,"remaining_time":21.96240002},
{"learn":[0.8889268617],"iteration":33,"passed_time":0.7649778674,"remaining_time":21.73437117},
{"learn":[0.888622681],"iteration":34,"passed_time":0.7820493881,"remaining_time":21.56221884},
{"learn":[0.8882313055],"iteration":35,"passed_time":0.8030060932,"remaining_time":21.50271872},
{"learn":[0.8880007523],"iteration":36,"passed_time":0.820159082,"remaining_time":21.34630259},
{"learn":[0.887605728],"iteration":37,"passed_time":0.835095066,"remaining_time":21.14109088},
{"learn":[0.8872020247],"iteration":38,"passed_time":0.8500290656,"remaining_time":20.945588},
{"learn":[0.887003111],"iteration":39,"passed_time":0.8673947133,"remaining_time":20.81747312},
{"learn":[0.8868212837],"iteration":40,"passed_time":0.8855217824,"remaining_time":20.71257047},
{"learn":[0.8866008408],"iteration":41,"passed_time":0.9021495848,"remaining_time":20.57760243},
{"learn":[0.8864308868],"iteration":42,"passed_time":0.9137651998,"remaining_time":20.33658828},
{"learn":[0.8862049553],"iteration":43,"passed_time":0.9296156914,"remaining_time":20.19801366},
{"learn":[0.8859810993],"iteration":44,"passed_time":0.9441025208,"remaining_time":20.0359535},
{"learn":[0.8857174027],"iteration":45,"passed_time":0.9570054839,"remaining_time":19.84746156},
{"learn":[0.8855219674],"iteration":46,"passed_time":0.974138565,"remaining_time":19.75221388},
{"learn":[0.8853371165],"iteration":47,"passed_time":0.9861315494,"remaining_time":19.55827573},
{"learn":[0.8851345272],"iteration":48,"passed_time":0.9991638956,"remaining_time":19.39193602},
{"learn":[0.8848985062],"iteration":49,"passed_time":1.015096081,"remaining_time":19.28682554},
{"learn":[0.8847248014],"iteration":50,"passed_time":1.032579931,"remaining_time":19.21408538},
{"learn":[0.8845721781],"iteration":51,"passed_time":1.045080608,"remaining_time":19.0526234},
{"learn":[0.8843817356],"iteration":52,"passed_time":1.060067638,"remaining_time":18.94120856},
{"learn":[0.8842054009],"iteration":53,"passed_time":1.076276824,"remaining_time":18.85477547},
{"learn":[0.8840779198],"iteration":54,"passed_time":1.089667153,"remaining_time":18.7224629},
{"learn":[0.8838802721],"iteration":55,"passed_time":1.103794246,"remaining_time":18.60681729},
{"learn":[0.8836510378],"iteration":56,"passed_time":1.12514916,"remaining_time":18.61430978},
{"learn":[0.8835336245],"iteration":57,"passed_time":1.145155901,"remaining_time":18.59891136},
{"learn":[0.8833902564],"iteration":58,"passed_time":1.172429105,"remaining_time":18.69925064},
{"learn":[0.8831837234],"iteration":59,"passed_time":1.190205805,"remaining_time":18.64655761},
{"learn":[0.8826954638],"iteration":60,"passed_time":1.208832503,"remaining_time":18.60809377},
{"learn":[0.8825782489],"iteration":61,"passed_time":1.226839277,"remaining_time":18.56089099},
{"learn":[0.8824960285],"iteration":62,"passed_time":1.24820478,"remaining_time":18.5645695},
{"learn":[0.8823657098],"iteration":63,"passed_time":1.2719738,"remaining_time":18.60261682},
{"learn":[0.8822056331],"iteration":64,"passed_time":1.288677885,"remaining_time":18.53713572},
{"learn":[0.882088121],"iteration":65,"passed_time":1.30625481,"remaining_time":18.48548474},
{"learn":[0.8817688445],"iteration":66,"passed_time":1.320731741,"remaining_time":18.39168231},
{"learn":[0.8816552503],"iteration":67,"passed_time":1.336701416,"remaining_time":18.32067235},
{"learn":[0.8815225155],"iteration":68,"passed_time":1.35135039,"remaining_time":18.23343787},
{"learn":[0.8814114493],"iteration":69,"passed_time":1.363652375,"remaining_time":18.11709583},
{"learn":[0.8813067362],"iteration":70,"passed_time":1.376523909,"remaining_time":18.01113678},
{"learn":[0.881224132],"iteration":71,"passed_time":1.389092935,"remaining_time":17.9038645},
{"learn":[0.8810883946],"iteration":72,"passed_time":1.403844282,"remaining_time":17.8268993},
{"learn":[0.8809380318],"iteration":73,"passed_time":1.418725492,"remaining_time":17.75324061},
{"learn":[0.8807769885],"iteration":74,"passed_time":1.435804141,"remaining_time":17.70825108},
{"learn":[0.8806892286],"iteration":75,"passed_time":1.450536862,"remaining_time":17.63547448},
{"learn":[0.8806074569],"iteration":76,"passed_time":1.465670186,"remaining_time":17.56900756},
{"learn":[0.8804943998],"iteration":77,"passed_time":1.47798257,"remaining_time":17.47051192},
{"learn":[0.8803552165],"iteration":78,"passed_time":1.492518221,"remaining_time":17.40011749},
{"learn":[0.8802839041],"iteration":79,"passed_time":1.506933105,"remaining_time":17.32973071},
{"learn":[0.8801952146],"iteration":80,"passed_time":1.522201714,"remaining_time":17.27041204},
{"learn":[0.8800824028],"iteration":81,"passed_time":1.537131296,"remaining_time":17.20837231},
{"learn":[0.8798991307],"iteration":82,"passed_time":1.554495246,"remaining_time":17.17436314},
{"learn":[0.8797717996],"iteration":83,"passed_time":1.571989771,"remaining_time":17.14217417},
{"learn":[0.8796262897],"iteration":84,"passed_time":1.589478737,"remaining_time":17.11027111},
{"learn":[0.8794447233],"iteration":85,"passed_time":1.604136792,"remaining_time":17.0486166},
{"learn":[0.8792542277],"iteration":86,"passed_time":1.619646123,"remaining_time":16.99697598},
{"learn":[0.8791055751],"iteration":87,"passed_time":1.636686189,"remaining_time":16.96202051},
{"learn":[0.8789591121],"iteration":88,"passed_time":1.65256809,"remaining_time":16.91561269},
{"learn":[0.8788699228],"iteration":89,"passed_time":1.666634409,"remaining_time":16.85152569},
{"learn":[0.8787406584],"iteration":90,"passed_time":1.678561008,"remaining_time":16.76716436},
{"learn":[0.8785072069],"iteration":91,"passed_time":1.697058864,"remaining_time":16.74923314},
{"learn":[0.8784217665],"iteration":92,"passed_time":1.712117829,"remaining_time":16.6977513},
{"learn":[0.8783285512],"iteration":93,"passed_time":1.727449224,"remaining_time":16.64967018},
{"learn":[0.8781216354],"iteration":94,"passed_time":1.75085415,"remaining_time":16.67918954},
{"learn":[0.8780406302],"iteration":95,"passed_time":1.766032629,"remaining_time":16.63014059},
{"learn":[0.8779363775],"iteration":96,"passed_time":1.782025117,"remaining_time":16.58936785},
{"learn":[0.8778602496],"iteration":97,"passed_time":1.798170048,"remaining_time":16.55050391},
{"learn":[0.8777303462],"iteration":98,"passed_time":1.815483643,"remaining_time":16.52273497},
{"learn":[0.8776084596],"iteration":99,"passed_time":1.830193337,"remaining_time":16.47174003},
{"learn":[0.8775327134],"iteration":100,"passed_time":1.847245491,"remaining_time":16.44231383},
{"learn":[0.8774096241],"iteration":101,"passed_time":1.866178424,"remaining_time":16.42968848},
{"learn":[0.8772850124],"iteration":102,"passed_time":1.881819572,"remaining_time":16.38827336},
{"learn":[0.8772194302],"iteration":103,"passed_time":1.897853378,"remaining_time":16.35073679},
{"learn":[0.8768202722],"iteration":104,"passed_time":1.916501477,"remaining_time":16.33589354},
{"learn":[0.8767280836],"iteration":105,"passed_time":1.952936875,"remaining_time":16.47099591},
{"learn":[0.8766827377],"iteration":106,"passed_time":1.969462094,"remaining_time":16.4367257},
{"learn":[0.8765292282],"iteration":107,"passed_time":1.997529706,"remaining_time":16.49811572},
{"learn":[0.8764093988],"iteration":108,"passed_time":2.014958678,"remaining_time":16.47090075},
{"learn":[0.876289891],"iteration":109,"passed_time":2.038114185,"remaining_time":16.49019659},
{"learn":[0.8761736474],"iteration":110,"passed_time":2.052300435,"remaining_time":16.43689267},
{"learn":[0.8761150787],"iteration":111,"passed_time":2.067757162,"remaining_time":16.39436035},
{"learn":[0.8760214592],"iteration":112,"passed_time":2.080759191,"remaining_time":16.33303896},
{"learn":[0.8759656817],"iteration":113,"passed_time":2.09242497,"remaining_time":16.26218003},
{"learn":[0.8757105803],"iteration":114,"passed_time":2.110731887,"remaining_time":16.24345843},
{"learn":[0.875640767],"iteration":115,"passed_time":2.1376854,"remaining_time":16.29063701},
{"learn":[0.875588958],"iteration":116,"passed_time":2.148084079,"remaining_time":16.2116089},
{"learn":[0.8754931525],"iteration":117,"passed_time":2.161639789,"remaining_time":16.15734147},
{"learn":[0.8753697148],"iteration":118,"passed_time":2.178000318,"remaining_time":16.12452336},
{"learn":[0.8753189294],"iteration":119,"passed_time":2.191531992,"remaining_time":16.07123461},
{"learn":[0.875210132],"iteration":120,"passed_time":2.212171363,"remaining_time":16.07023659},
{"learn":[0.8751470483],"iteration":121,"passed_time":2.226537685,"remaining_time":16.02377121},
{"learn":[0.8750582022],"iteration":122,"passed_time":2.244993071,"remaining_time":16.00698311},
{"learn":[0.8749693844],"iteration":123,"passed_time":2.261958848,"remaining_time":15.97964477},
{"learn":[0.8749170192],"iteration":124,"passed_time":2.27505758,"remaining_time":15.92540306},
{"learn":[0.8748029453],"iteration":125,"passed_time":2.28904434,"remaining_time":15.87797423},
{"learn":[0.874704123],"iteration":126,"passed_time":2.301804916,"remaining_time":15.82264324},
{"learn":[0.8745732406],"iteration":127,"passed_time":2.317402833,"remaining_time":15.7873068},
{"learn":[0.8745194342],"iteration":128,"passed_time":2.333318567,"remaining_time":15.75442226},
{"learn":[0.8744509451],"iteration":129,"passed_time":2.348979502,"remaining_time":15.72009359},
{"learn":[0.8743603693],"iteration":130,"passed_time":2.362086679,"remaining_time":15.66910934},
{"learn":[0.8742747739],"iteration":131,"passed_time":2.383558533,"remaining_time":15.67370308},
{"learn":[0.8741834248],"iteration":132,"passed_time":2.394414405,"remaining_time":15.60870142},
{"learn":[0.8741237415],"iteration":133,"passed_time":2.405230592,"remaining_time":15.54425144},
{"learn":[0.8738454583],"iteration":134,"passed_time":2.415787898,"remaining_time":15.47893727},
{"learn":[0.8736887518],"iteration":135,"passed_time":2.425733996,"remaining_time":15.41054539},
{"learn":[0.8735818553],"iteration":136,"passed_time":2.434612438,"remaining_time":15.33628127},
{"learn":[0.8735216371],"iteration":137,"passed_time":2.443880036,"remaining_time":15.26539559},
{"learn":[0.8734686889],"iteration":138,"passed_time":2.455092608,"remaining_time":15.20744414},
{"learn":[0.8733038418],"iteration":139,"passed_time":2.46852953,"remaining_time":15.16382426},
{"learn":[0.873177977],"iteration":140,"passed_time":2.480492693,"remaining_time":15.11165406},
{"learn":[0.8730488545],"iteration":141,"passed_time":2.490090916,"remaining_time":15.04576061},
{"learn":[0.8729362444],"iteration":142,"passed_time":2.503373564,"remaining_time":15.00273527},
{"learn":[0.8728556762],"iteration":143,"passed_time":2.514726244,"remaining_time":14.94865045},
{"learn":[0.8727232719],"iteration":144,"passed_time":2.525201696,"remaining_time":14.88998242},
{"learn":[0.8726278328],"iteration":145,"passed_time":2.536619139,"remaining_time":14.83748455},
{"learn":[0.8725127722],"iteration":146,"passed_time":2.547667768,"remaining_time":14.78340549},
{"learn":[0.8723655442],"iteration":147,"passed_time":2.561127799,"remaining_time":14.74378976},
{"learn":[0.8721495399],"iteration":148,"passed_time":2.576930991,"remaining_time":14.71790788},
{"learn":[0.872065603],"iteration":149,"passed_time":2.589540093,"remaining_time":14.67406053},
{"learn":[0.8719716056],"iteration":150,"passed_time":2.604155473,"remaining_time":14.64190726},
{"learn":[0.871924659],"iteration":151,"passed_time":2.619481329,"remaining_time":14.61394847},
{"learn":[0.8718366844],"iteration":152,"passed_time":2.633925689,"remaining_time":14.58127489},
{"learn":[0.8717623636],"iteration":153,"passed_time":2.654319688,"remaining_time":14.58152244},
{"learn":[0.8716900518],"iteration":154,"passed_time":2.668145124,"remaining_time":14.54569438},
{"learn":[0.8716214368],"iteration":155,"passed_time":2.678911683,"remaining_time":14.49359911},
{"learn":[0.8715078039],"iteration":156,"passed_time":2.693144396,"remaining_time":14.46064156},
{"learn":[0.8714497054],"iteration":157,"passed_time":2.705401065,"remaining_time":14.41739048},
{"learn":[0.8713450801],"iteration":158,"passed_time":2.713654773,"remaining_time":14.35335638},
{"learn":[0.8712940999],"iteration":159,"passed_time":2.722213343,"remaining_time":14.29162005},
{"learn":[0.8712328768],"iteration":160,"passed_time":2.730679149,"remaining_time":14.23006091},
{"learn":[0.8711529662],"iteration":161,"passed_time":2.741602343,"remaining_time":14.18186891},
{"learn":[0.8710859574],"iteration":162,"passed_time":2.752173806,"remaining_time":14.13232807},
{"learn":[0.8709956015],"iteration":163,"passed_time":2.760776599,"remaining_time":14.07322706},
{"learn":[0.8708707565],"iteration":164,"passed_time":2.774698608,"remaining_time":14.04165659},
{"learn":[0.8707766664],"iteration":165,"passed_time":2.784415314,"remaining_time":13.98917092},
{"learn":[0.8706771867],"iteration":166,"passed_time":2.793821047,"remaining_time":13.9356463},
{"learn":[0.8705783191],"iteration":167,"passed_time":2.803768958,"remaining_time":13.88533198},
{"learn":[0.8704535325],"iteration":168,"passed_time":2.815760118,"remaining_time":13.84554236},
{"learn":[0.8703105179],"iteration":169,"passed_time":2.824353064,"remaining_time":13.78948849},
{"learn":[0.8702430461],"iteration":170,"passed_time":2.834194185,"remaining_time":13.74004081},
{"learn":[0.8701263631],"iteration":171,"passed_time":2.845012191,"remaining_time":13.69575636},
{"learn":[0.870020271],"iteration":172,"passed_time":2.856137324,"remaining_time":13.65332697},
{"learn":[0.8699025112],"iteration":173,"passed_time":2.866278768,"remaining_time":13.60658772},
{"learn":[0.869747006],"iteration":174,"passed_time":2.876526202,"remaining_time":13.56076638},
{"learn":[0.869590687],"iteration":175,"passed_time":2.884791572,"remaining_time":13.50606963},
{"learn":[0.8694708887],"iteration":176,"passed_time":2.895386849,"remaining_time":13.46273094},
{"learn":[0.8694414998],"iteration":177,"passed_time":2.905190249,"remaining_time":13.41610329},
{"learn":[0.8693478794],"iteration":178,"passed_time":2.916334404,"remaining_time":13.37603657},
{"learn":[0.8692718902],"iteration":179,"passed_time":2.928449341,"remaining_time":13.34071366},
{"learn":[0.8692228062],"iteration":180,"passed_time":2.93995553,"remaining_time":13.3028927},
{"learn":[0.8691426434],"iteration":181,"passed_time":2.953407816,"remaining_time":13.27410766},
{"learn":[0.8690698872],"iteration":182,"passed_time":2.964614953,"remaining_time":13.23546676},
{"learn":[0.8689798741],"iteration":183,"passed_time":2.974974437,"remaining_time":13.19336489},
{"learn":[0.8688815976],"iteration":184,"passed_time":2.990799912,"remaining_time":13.1756861},
{"learn":[0.8688249595],"iteration":185,"passed_time":3.003576553,"remaining_time":13.14468448},
{"learn":[0.8687068064],"iteration":186,"passed_time":3.018704056,"remaining_time":13.12409838},
{"learn":[0.8686074522],"iteration":187,"passed_time":3.034371273,"remaining_time":13.10590146},
{"learn":[0.868516734],"iteration":188,"passed_time":3.04629704,"remaining_time":13.07167672},
{"learn":[0.8684097396],"iteration":189,"passed_time":3.060861175,"remaining_time":13.04893448},
{"learn":[0.8683575421],"iteration":190,"passed_time":3.072776403,"remaining_time":13.01505817},
{"learn":[0.8682570293],"iteration":191,"passed_time":3.086805501,"remaining_time":12.99030649},
{"learn":[0.8681657626],"iteration":192,"passed_time":3.100460708,"remaining_time":12.96410255},
{"learn":[0.8680319405],"iteration":193,"passed_time":3.114141875,"remaining_time":12.93813583},
{"learn":[0.867970295],"iteration":194,"passed_time":3.129212065,"remaining_time":12.91802929},
{"learn":[0.8678830374],"iteration":195,"passed_time":3.142417712,"remaining_time":12.89032572},
{"learn":[0.8677268437],"iteration":196,"passed_time":3.155875979,"remaining_time":12.86379904},
{"learn":[0.8676588252],"iteration":197,"passed_time":3.168595082,"remaining_time":12.83441038},
{"learn":[0.8675758165],"iteration":198,"passed_time":3.179887469,"remaining_time":12.79944655},
{"learn":[0.8675133866],"iteration":199,"passed_time":3.191084938,"remaining_time":12.76433975},
{"learn":[0.8674263168],"iteration":200,"passed_time":3.203017589,"remaining_time":12.7323933},
{"learn":[0.8673257036],"iteration":201,"passed_time":3.211856947,"remaining_time":12.68842497},
{"learn":[0.8672094058],"iteration":202,"passed_time":3.224768132,"remaining_time":12.66078917},
{"learn":[0.8671477377],"iteration":203,"passed_time":3.23515899,"remaining_time":12.62346351},
{"learn":[0.8670335874],"iteration":204,"passed_time":3.246709242,"remaining_time":12.59089682},
{"learn":[0.8669469729],"iteration":205,"passed_time":3.256641689,"remaining_time":12.55229855},
{"learn":[0.8667906849],"iteration":206,"passed_time":3.269263098,"remaining_time":12.52427844},
{"learn":[0.8667320159],"iteration":207,"passed_time":3.281270444,"remaining_time":12.49406823},
{"learn":[0.8666717059],"iteration":208,"passed_time":3.290354147,"remaining_time":12.45296713},
{"learn":[0.8666245937],"iteration":209,"passed_time":3.299700027,"remaining_time":12.41315724},
{"learn":[0.8664660636],"iteration":210,"passed_time":3.311528782,"remaining_time":12.38292042},
{"learn":[0.8663897507],"iteration":211,"passed_time":3.320839645,"remaining_time":12.3434983},
{"learn":[0.8663166994],"iteration":212,"passed_time":3.331047846,"remaining_time":12.30767443},
{"learn":[0.8662412793],"iteration":213,"passed_time":3.342292583,"remaining_time":12.27589706},
{"learn":[0.866127622],"iteration":214,"passed_time":3.353081936,"remaining_time":12.242648},
{"learn":[0.8660456421],"iteration":215,"passed_time":3.362144805,"remaining_time":12.2033404},
{"learn":[0.8659604701],"iteration":216,"passed_time":3.371871029,"remaining_time":12.16670514},
{"learn":[0.8658833079],"iteration":217,"passed_time":3.382292239,"remaining_time":12.13280977},
{"learn":[0.8658169048],"iteration":218,"passed_time":3.393647394,"remaining_time":12.10245943},
{"learn":[0.865755055],"iteration":219,"passed_time":3.403107158,"remaining_time":12.06556174},
{"learn":[0.8656673836],"iteration":220,"passed_time":3.411406252,"remaining_time":12.02482113},
{"learn":[0.8655718835],"iteration":221,"passed_time":3.421225571,"remaining_time":11.98970042},
{"learn":[0.8655339944],"iteration":222,"passed_time":3.430516869,"remaining_time":11.95296685},
{"learn":[0.8654514987],"iteration":223,"passed_time":3.441165025,"remaining_time":11.92117884},
{"learn":[0.8654025946],"iteration":224,"passed_time":3.454417732,"remaining_time":11.89854996},
{"learn":[0.8653046165],"iteration":225,"passed_time":3.46489383,"remaining_time":11.8664948},
{"learn":[0.8652595474],"iteration":226,"passed_time":3.473658378,"remaining_time":11.82880144},
{"learn":[0.8651426816],"iteration":227,"passed_time":3.483975403,"remaining_time":11.79661847},
{"learn":[0.865102953],"iteration":228,"passed_time":3.496488925,"remaining_time":11.77202166},
{"learn":[0.8650404931],"iteration":229,"passed_time":3.506118708,"remaining_time":11.73787567},
{"learn":[0.865009707],"iteration":230,"passed_time":3.517769047,"remaining_time":11.71066839},
{"learn":[0.8649166754],"iteration":231,"passed_time":3.528145954,"remaining_time":11.67937971},
{"learn":[0.8648460419],"iteration":232,"passed_time":3.538161258,"remaining_time":11.64708019},
{"learn":[0.8647223067],"iteration":233,"passed_time":3.551871057,"remaining_time":11.62706509},
{"learn":[0.8646335381],"iteration":234,"passed_time":3.567144619,"remaining_time":11.61219419},
{"learn":[0.8645869005],"iteration":235,"passed_time":3.57648045,"remaining_time":11.57809773},
{"learn":[0.8644986528],"iteration":236,"passed_time":3.587059403,"remaining_time":11.54821234},
{"learn":[0.8643415544],"iteration":237,"passed_time":3.600336384,"remaining_time":11.52712741},
{"learn":[0.8642597415],"iteration":238,"passed_time":3.61192072,"remaining_time":11.50071828},
{"learn":[0.8641675729],"iteration":239,"passed_time":3.622614202,"remaining_time":11.47161164},
{"learn":[0.8641076052],"iteration":240,"passed_time":3.634954138,"remaining_time":11.44784311},
{"learn":[0.8640075651],"iteration":241,"passed_time":3.645464666,"remaining_time":11.41843891},
{"learn":[0.8639218339],"iteration":242,"passed_time":3.654867001,"remaining_time":11.38573794},
{"learn":[0.8638598666],"iteration":243,"passed_time":3.665071234,"remaining_time":11.35571251},
{"learn":[0.8637747134],"iteration":244,"passed_time":3.677700503,"remaining_time":11.33332196},
{"learn":[0.8636960101],"iteration":245,"passed_time":3.689736578,"remaining_time":11.3091926},
{"learn":[0.8635981819],"iteration":246,"passed_time":3.703728167,"remaining_time":11.29112271},
{"learn":[0.8634923249],"iteration":247,"passed_time":3.719049455,"remaining_time":11.2771177},
{"learn":[0.8634123352],"iteration":248,"passed_time":3.731726343,"remaining_time":11.25512644},
{"learn":[0.8633341849],"iteration":249,"passed_time":3.742533078,"remaining_time":11.22759923},
{"learn":[0.8632841878],"iteration":250,"passed_time":3.753145849,"remaining_time":11.19962646},
{"learn":[0.8632025693],"iteration":251,"passed_time":3.764082808,"remaining_time":11.17275373},
{"learn":[0.8631237168],"iteration":252,"passed_time":3.776054342,"remaining_time":11.14906163},
{"learn":[0.8630451052],"iteration":253,"passed_time":3.798786914,"remaining_time":11.15706708},
{"learn":[0.8629885863],"iteration":254,"passed_time":3.811166164,"remaining_time":11.1345835},
{"learn":[0.8629280105],"iteration":255,"passed_time":3.823112751,"remaining_time":11.11092143},
{"learn":[0.8628697762],"iteration":256,"passed_time":3.839341643,"remaining_time":11.0997309},
{"learn":[0.8628086187],"iteration":257,"passed_time":3.850381216,"remaining_time":11.07357698},
{"learn":[0.8627425244],"iteration":258,"passed_time":3.86337762,"remaining_time":11.05313829},
{"learn":[0.8626900308],"iteration":259,"passed_time":3.87433882,"remaining_time":11.02696433},
{"learn":[0.8626155731],"iteration":260,"passed_time":3.886301386,"remaining_time":11.00374224},
{"learn":[0.8625396783],"iteration":261,"passed_time":3.897000218,"remaining_time":10.97704641},
{"learn":[0.8624639417],"iteration":262,"passed_time":3.906926278,"remaining_time":10.94830672},
{"learn":[0.8624113183],"iteration":263,"passed_time":3.917726291,"remaining_time":10.92214602},
{"learn":[0.8622938219],"iteration":264,"passed_time":3.928747798,"remaining_time":10.89671559},
{"learn":[0.8622281033],"iteration":265,"passed_time":3.940747736,"remaining_time":10.87409338},
{"learn":[0.8621517559],"iteration":266,"passed_time":3.952344785,"remaining_time":10.85044467},
{"learn":[0.8620795491],"iteration":267,"passed_time":3.965608567,"remaining_time":10.83143832},
{"learn":[0.8620365767],"iteration":268,"passed_time":3.975166585,"remaining_time":10.80240436},
{"learn":[0.8619946364],"iteration":269,"passed_time":3.986225104,"remaining_time":10.77757158},
{"learn":[0.8618904595],"iteration":270,"passed_time":3.996102302,"remaining_time":10.74966265},
{"learn":[0.86181386],"iteration":271,"passed_time":4.006696808,"remaining_time":10.72380616},
{"learn":[0.8617077252],"iteration":272,"passed_time":4.016828414,"remaining_time":10.69682878},
{"learn":[0.8616115374],"iteration":273,"passed_time":4.027680023,"remaining_time":10.6718821},
{"learn":[0.8615485883],"iteration":274,"passed_time":4.037842307,"remaining_time":10.64522063},
{"learn":[0.8614650346],"iteration":275,"passed_time":4.047637912,"remaining_time":10.61771684},
{"learn":[0.8614096532],"iteration":276,"passed_time":4.056962372,"remaining_time":10.58911117},
{"learn":[0.8613651431],"iteration":277,"passed_time":4.068261873,"remaining_time":10.56577364},
{"learn":[0.8612883416],"iteration":278,"passed_time":4.079488897,"remaining_time":10.54233511},
{"learn":[0.8611508142],"iteration":279,"passed_time":4.088249748,"remaining_time":10.51264221},
{"learn":[0.8610667958],"iteration":280,"passed_time":4.096879993,"remaining_time":10.48276411},
{"learn":[0.8610169373],"iteration":281,"passed_time":4.106176611,"remaining_time":10.45473336},
{"learn":[0.860978414],"iteration":282,"passed_time":4.115388609,"remaining_time":10.42662061},
{"learn":[0.8609069853],"iteration":283,"passed_time":4.126451084,"remaining_time":10.40330626},
{"learn":[0.8608171871],"iteration":284,"passed_time":4.140134534,"remaining_time":10.38665331},
{"learn":[0.860760033],"iteration":285,"passed_time":4.149484272,"remaining_time":10.35920199},
{"learn":[0.8607284721],"iteration":286,"passed_time":4.15814251,"remaining_time":10.33015892},
{"learn":[0.8606861931],"iteration":287,"passed_time":4.168139764,"remaining_time":10.30456775},
{"learn":[0.860637704],"iteration":288,"passed_time":4.177067198,"remaining_time":10.27645252},
{"learn":[0.8605828714],"iteration":289,"passed_time":4.186434273,"remaining_time":10.24954598},
{"learn":[0.8605256547],"iteration":290,"passed_time":4.198069033,"remaining_time":10.22828503},
{"learn":[0.8604597235],"iteration":291,"passed_time":4.20728327,"remaining_time":10.20122108},
{"learn":[0.8603277162],"iteration":292,"passed_time":4.21665017,"remaining_time":10.17464734},
{"learn":[0.860287641],"iteration":293,"passed_time":4.225824698,"remaining_time":10.1477287},
{"learn":[0.8601969354],"iteration":294,"passed_time":4.235926378,"remaining_time":10.12314609},
{"learn":[0.8601441864],"iteration":295,"passed_time":4.247793906,"remaining_time":10.10286118},
{"learn":[0.8600753661],"iteration":296,"passed_time":4.259260922,"remaining_time":10.08168494},
{"learn":[0.8599835605],"iteration":297,"passed_time":4.272914661,"remaining_time":10.06572514},
{"learn":[0.8599326526],"iteration":298,"passed_time":4.28420489,"remaining_time":10.04423956},
{"learn":[0.8598834811],"iteration":299,"passed_time":4.297362682,"remaining_time":10.02717959},
{"learn":[0.8597916485],"iteration":300,"passed_time":4.308385773,"remaining_time":10.00518822},
{"learn":[0.8597271925],"iteration":301,"passed_time":4.319182228,"remaining_time":9.98274568},
{"learn":[0.8596162814],"iteration":302,"passed_time":4.33051936,"remaining_time":9.961623743},
{"learn":[0.8595490415],"iteration":303,"passed_time":4.341234473,"remaining_time":9.939142082},
{"learn":[0.859502],"iteration":304,"passed_time":4.353274946,"remaining_time":9.919757663},
{"learn":[0.8594236101],"iteration":305,"passed_time":4.364680726,"remaining_time":9.898981778},
{"learn":[0.859370825],"iteration":306,"passed_time":4.37571591,"remaining_time":9.877430376},
{"learn":[0.8590848764],"iteration":307,"passed_time":4.386383834,"remaining_time":9.855122121},
{"learn":[0.8589994611],"iteration":308,"passed_time":4.40285951,"remaining_time":9.845876769},
{"learn":[0.858939209],"iteration":309,"passed_time":4.416955545,"remaining_time":9.831288149},
{"learn":[0.8588758354],"iteration":310,"passed_time":4.426274194,"remaining_time":9.806118713},
{"learn":[0.8588219846],"iteration":311,"passed_time":4.438531324,"remaining_time":9.787530612},
{"learn":[0.8587188309],"iteration":312,"passed_time":4.450465302,"remaining_time":9.768273683},
{"learn":[0.8586639431],"iteration":313,"passed_time":4.460480325,"remaining_time":9.744871028},
{"learn":[0.8586181149],"iteration":314,"passed_time":4.478129405,"remaining_time":9.738154421},
{"learn":[0.8585118852],"iteration":315,"passed_time":4.490515323,"remaining_time":9.719976205},
{"learn":[0.8583893043],"iteration":316,"passed_time":4.505356222,"remaining_time":9.707123973},
{"learn":[0.8583541654],"iteration":317,"passed_time":4.515564062,"remaining_time":9.684322925},
{"learn":[0.8582371701],"iteration":318,"passed_time":4.526152977,"remaining_time":9.66241435},
{"learn":[0.8581775415],"iteration":319,"passed_time":4.538306983,"remaining_time":9.643902339},
{"learn":[0.8581332846],"iteration":320,"passed_time":4.550219456,"remaining_time":9.624919036},
{"learn":[0.8580893923],"iteration":321,"passed_time":4.559987899,"remaining_time":9.601465204},
{"learn":[0.8580506862],"iteration":322,"passed_time":4.569931493,"remaining_time":9.578463222},
{"learn":[0.8579475133],"iteration":323,"passed_time":4.580834598,"remaining_time":9.557543792},
{"learn":[0.857859751],"iteration":324,"passed_time":4.591104996,"remaining_time":9.535371914},
{"learn":[0.8578054468],"iteration":325,"passed_time":4.60087918,"remaining_time":9.51224714},
{"learn":[0.8577547356],"iteration":326,"passed_time":4.610854223,"remaining_time":9.489617407},
{"learn":[0.8576921784],"iteration":327,"passed_time":4.62025717,"remaining_time":9.465892739},
{"learn":[0.857597078],"iteration":328,"passed_time":4.629188821,"remaining_time":9.441293919},
{"learn":[0.8575506695],"iteration":329,"passed_time":4.637483797,"remaining_time":9.415497406},
{"learn":[0.8574808725],"iteration":330,"passed_time":4.646604494,"remaining_time":9.391475548},
{"learn":[0.8574317406],"iteration":331,"passed_time":4.657018932,"remaining_time":9.370146525},
{"learn":[0.8573447347],"iteration":332,"passed_time":4.668503942,"remaining_time":9.351027414},
{"learn":[0.85727394],"iteration":333,"passed_time":4.678340363,"remaining_time":9.328666711},
{"learn":[0.8572056782],"iteration":334,"passed_time":4.688447493,"remaining_time":9.306918158},
{"learn":[0.8569724117],"iteration":335,"passed_time":4.698505571,"remaining_time":9.285141962},
{"learn":[0.8568934518],"iteration":336,"passed_time":4.70978262,"remaining_time":9.265833462},
{"learn":[0.8568244939],"iteration":337,"passed_time":4.722517347,"remaining_time":9.249427467},
{"learn":[0.8567793426],"iteration":338,"passed_time":4.733011845,"remaining_time":9.228675014},
{"learn":[0.8567117094],"iteration":339,"passed_time":4.742687506,"remaining_time":9.206393393},
{"learn":[0.856666605],"iteration":340,"passed_time":4.752037513,"remaining_time":9.183556367},
{"learn":[0.856611806],"iteration":341,"passed_time":4.761947142,"remaining_time":9.16187491},
{"learn":[0.8565522881],"iteration":342,"passed_time":4.77145708,"remaining_time":9.139496506},
{"learn":[0.8564967752],"iteration":343,"passed_time":4.781776419,"remaining_time":9.118736427},
{"learn":[0.8564658081],"iteration":344,"passed_time":4.79029767,"remaining_time":9.094623112},
{"learn":[0.8564147623],"iteration":345,"passed_time":4.799558891,"remaining_time":9.071998597},
{"learn":[0.856377346],"iteration":346,"passed_time":4.809265379,"remaining_time":9.050289028},
{"learn":[0.8563153049],"iteration":347,"passed_time":4.818075432,"remaining_time":9.026968914},
{"learn":[0.8560678172],"iteration":348,"passed_time":4.828923023,"remaining_time":9.007532631},
{"learn":[0.8560076094],"iteration":349,"passed_time":4.838398467,"remaining_time":8.985597153},
{"learn":[0.855924887],"iteration":350,"passed_time":4.848271097,"remaining_time":8.964467071},
{"learn":[0.8558801884],"iteration":351,"passed_time":4.857870443,"remaining_time":8.942897861},
{"learn":[0.8558228163],"iteration":352,"passed_time":4.866994887,"remaining_time":8.92052604},
{"learn":[0.8557592587],"iteration":353,"passed_time":4.876979427,"remaining_time":8.899798616},
{"learn":[0.8557379971],"iteration":354,"passed_time":4.885509354,"remaining_time":8.876488827},
{"learn":[0.8556739752],"iteration":355,"passed_time":4.895057714,"remaining_time":8.855104404},
{"learn":[0.8554459413],"iteration":356,"passed_time":4.905989895,"remaining_time":8.836278719},
{"learn":[0.8554111391],"iteration":357,"passed_time":4.915086036,"remaining_time":8.814204567},
{"learn":[0.8553250674],"iteration":358,"passed_time":4.924731028,"remaining_time":8.793182699},
{"learn":[0.8552711253],"iteration":359,"passed_time":4.933734745,"remaining_time":8.771083992},
{"learn":[0.8552088082],"iteration":360,"passed_time":4.94156115,"remaining_time":8.746973892},
{"learn":[0.855131706],"iteration":361,"passed_time":4.951669493,"remaining_time":8.726975516},
{"learn":[0.8550518537],"iteration":362,"passed_time":4.963094961,"remaining_time":8.709342948},
{"learn":[0.8549406315],"iteration":363,"passed_time":4.974384643,"remaining_time":8.691507233},
{"learn":[0.8548951755],"iteration":364,"passed_time":4.986136483,"remaining_time":8.674511416},
{"learn":[0.8548578036],"iteration":365,"passed_time":4.993737676,"remaining_time":8.650354334},
{"learn":[0.8547577457],"iteration":366,"passed_time":5.004686116,"remaining_time":8.632060794},
{"learn":[0.8547117048],"iteration":367,"passed_time":5.015958997,"remaining_time":8.614364364},
{"learn":[0.8546157314],"iteration":368,"passed_time":5.029090595,"remaining_time":8.599881208},
{"learn":[0.8545117029],"iteration":369,"passed_time":5.044251356,"remaining_time":8.588860417},
{"learn":[0.8544711019],"iteration":370,"passed_time":5.05755393,"remaining_time":8.574666906},
{"learn":[0.8544001094],"iteration":371,"passed_time":5.070606861,"remaining_time":8.560056743},
{"learn":[0.8543407039],"iteration":372,"passed_time":5.082261929,"remaining_time":8.543105173},
{"learn":[0.8543004471],"iteration":373,"passed_time":5.092660742,"remaining_time":8.52407921},
{"learn":[0.8542350496],"iteration":374,"passed_time":5.103539162,"remaining_time":8.505898603},
{"learn":[0.8541763318],"iteration":375,"passed_time":5.114106106,"remaining_time":8.48723992},
{"learn":[0.8541179006],"iteration":376,"passed_time":5.123543448,"remaining_time":8.466757475},
{"learn":[0.8540389925],"iteration":377,"passed_time":5.137550616,"remaining_time":8.45385313},
{"learn":[0.8539518516],"iteration":378,"passed_time":5.152364109,"remaining_time":8.442264147},
{"learn":[0.8539060138],"iteration":379,"passed_time":5.163523527,"remaining_time":8.424696281},
{"learn":[0.8538511956],"iteration":380,"passed_time":5.174204515,"remaining_time":8.406384764},
{"learn":[0.8538087021],"iteration":381,"passed_time":5.182678207,"remaining_time":8.38454223},
{"learn":[0.8537652719],"iteration":382,"passed_time":5.192519938,"remaining_time":8.364973374},
{"learn":[0.8536427334],"iteration":383,"passed_time":5.202812216,"remaining_time":8.34617793},
{"learn":[0.8535767499],"iteration":384,"passed_time":5.223699942,"remaining_time":8.344351856},
{"learn":[0.8535249741],"iteration":385,"passed_time":5.238274016,"remaining_time":8.332384056},
{"learn":[0.853469681],"iteration":386,"passed_time":5.250847821,"remaining_time":8.317234403},
{"learn":[0.8533890267],"iteration":387,"passed_time":5.26479135,"remaining_time":8.304258521},
{"learn":[0.8532963272],"iteration":388,"passed_time":5.280545871,"remaining_time":8.294122177},
{"learn":[0.8532213117],"iteration":389,"passed_time":5.29274399,"remaining_time":8.278394446},
{"learn":[0.8531989498],"iteration":390,"passed_time":5.305807194,"remaining_time":8.264032177},
{"learn":[0.8531129395],"iteration":391,"passed_time":5.320165332,"remaining_time":8.251685005},
{"learn":[0.8530268952],"iteration":392,"passed_time":5.338812709,"remaining_time":8.245952453},
{"learn":[0.8529986696],"iteration":393,"passed_time":5.351111026,"remaining_time":8.23038904},
{"learn":[0.8529185678],"iteration":394,"passed_time":5.366788152,"remaining_time":8.220017296},
{"learn":[0.8528775688],"iteration":395,"passed_time":5.382613546,"remaining_time":8.209844904},
{"learn":[0.8528398371],"iteration":396,"passed_time":5.395772491,"remaining_time":8.195593986},
{"learn":[0.8527732874],"iteration":397,"passed_time":5.410979613,"remaining_time":8.184446551},
{"learn":[0.8526787307],"iteration":398,"passed_time":5.424904537,"remaining_time":8.171347436},
{"learn":[0.8526152056],"iteration":399,"passed_time":5.440296617,"remaining_time":8.160444926},
{"learn":[0.8525473637],"iteration":400,"passed_time":5.455648603,"remaining_time":8.149460133},
{"learn":[0.8524883331],"iteration":401,"passed_time":5.471228876,"remaining_time":8.138793204},
{"learn":[0.8524281365],"iteration":402,"passed_time":5.483156102,"remaining_time":8.122690305},
{"learn":[0.8523688986],"iteration":403,"passed_time":5.494460517,"remaining_time":8.105689277},
{"learn":[0.8522846459],"iteration":404,"passed_time":5.509268399,"remaining_time":8.09386345},
{"learn":[0.8522126801],"iteration":405,"passed_time":5.526159305,"remaining_time":8.085070511},
{"learn":[0.8521551038],"iteration":406,"passed_time":5.539976021,"remaining_time":8.071758675},
{"learn":[0.8520943039],"iteration":407,"passed_time":5.557591153,"remaining_time":8.06395579},
{"learn":[0.8520413057],"iteration":408,"passed_time":5.569842483,"remaining_time":8.048354296},
{"learn":[0.8520008854],"iteration":409,"passed_time":5.578820791,"remaining_time":8.028059187},
{"learn":[0.8519526083],"iteration":410,"passed_time":5.597138809,"remaining_time":8.021203792},
{"learn":[0.8519215466],"iteration":411,"passed_time":5.610692766,"remaining_time":8.007493559},
{"learn":[0.8518788294],"iteration":412,"passed_time":5.621571717,"remaining_time":7.989982077},
{"learn":[0.8518063088],"iteration":413,"passed_time":5.636795961,"remaining_time":7.97865322},
{"learn":[0.8517103452],"iteration":414,"passed_time":5.649558186,"remaining_time":7.963835033},
{"learn":[0.8516640916],"iteration":415,"passed_time":5.668707209,"remaining_time":7.957992813},
{"learn":[0.8516194831],"iteration":416,"passed_time":5.682983439,"remaining_time":7.945274208},
{"learn":[0.8515505342],"iteration":417,"passed_time":5.697549161,"remaining_time":7.932951225},
{"learn":[0.8514890977],"iteration":418,"passed_time":5.715586191,"remaining_time":7.925430971},
{"learn":[0.8513869312],"iteration":419,"passed_time":5.73096159,"remaining_time":7.914185052},
{"learn":[0.8513167174],"iteration":420,"passed_time":5.746893925,"remaining_time":7.903685469},
{"learn":[0.8512808264],"iteration":421,"passed_time":5.762307726,"remaining_time":7.892449919},
{"learn":[0.8512344811],"iteration":422,"passed_time":5.777654246,"remaining_time":7.881102837},
{"learn":[0.8511300655],"iteration":423,"passed_time":5.794687385,"remaining_time":7.872028145},
{"learn":[0.8510915517],"iteration":424,"passed_time":5.812316558,"remaining_time":7.863722402},
{"learn":[0.850952981],"iteration":425,"passed_time":5.83099895,"remaining_time":7.856792013},
{"learn":[0.8509073198],"iteration":426,"passed_time":5.842929537,"remaining_time":7.840746193},
{"learn":[0.850876379],"iteration":427,"passed_time":5.857745224,"remaining_time":7.828575393},
{"learn":[0.8508022511],"iteration":428,"passed_time":5.870745821,"remaining_time":7.813976372},
{"learn":[0.8507683566],"iteration":429,"passed_time":5.88144548,"remaining_time":7.796334706},
{"learn":[0.850710079],"iteration":430,"passed_time":5.893426576,"remaining_time":7.780416988},
{"learn":[0.8506382659],"iteration":431,"passed_time":5.910320959,"remaining_time":7.770977557},
{"learn":[0.850587914],"iteration":432,"passed_time":5.925158192,"remaining_time":7.758809919},
{"learn":[0.8505358109],"iteration":433,"passed_time":5.93871006,"remaining_time":7.744953672},
{"learn":[0.8504641142],"iteration":434,"passed_time":5.95266511,"remaining_time":7.731622499},
{"learn":[0.8504264792],"iteration":435,"passed_time":5.964920272,"remaining_time":7.716089526},
{"learn":[0.8503311329],"iteration":436,"passed_time":5.978071076,"remaining_time":7.701725436},
{"learn":[0.8502252258],"iteration":437,"passed_time":5.992094715,"remaining_time":7.688486826},
{"learn":[0.8501834754],"iteration":438,"passed_time":6.005876549,"remaining_time":7.674935635},
{"learn":[0.8501071839],"iteration":439,"passed_time":6.018174926,"remaining_time":7.659495361},
{"learn":[0.8500483107],"iteration":440,"passed_time":6.031468063,"remaining_time":7.645330266},
{"learn":[0.8500248047],"iteration":441,"passed_time":6.043792716,"remaining_time":7.62994646},
{"learn":[0.8499449098],"iteration":442,"passed_time":6.056866384,"remaining_time":7.61551823},
{"learn":[0.8498857184],"iteration":443,"passed_time":6.068401458,"remaining_time":7.599169393},
{"learn":[0.8498414958],"iteration":444,"passed_time":6.07903074,"remaining_time":7.581712495},
{"learn":[0.8498178997],"iteration":445,"passed_time":6.089848986,"remaining_time":7.564520937},
{"learn":[0.8497673721],"iteration":446,"passed_time":6.101796824,"remaining_time":7.548755355},
{"learn":[0.8497338664],"iteration":447,"passed_time":6.11499341,"remaining_time":7.534545451},
{"learn":[0.8496756076],"iteration":448,"passed_time":6.129290111,"remaining_time":7.521690092},
{"learn":[0.8496035576],"iteration":449,"passed_time":6.141138343,"remaining_time":7.505835753},
{"learn":[0.8495171546],"iteration":450,"passed_time":6.153616399,"remaining_time":7.49076586},
{"learn":[0.8494883177],"iteration":451,"passed_time":6.165526753,"remaining_time":7.47501916},
{"learn":[0.8494534599],"iteration":452,"passed_time":6.178444889,"remaining_time":7.460506301},
{"learn":[0.8494189886],"iteration":453,"passed_time":6.190610507,"remaining_time":7.445095456},
{"learn":[0.8493643642],"iteration":454,"passed_time":6.202968106,"remaining_time":7.42992883},
{"learn":[0.8493194525],"iteration":455,"passed_time":6.216033424,"remaining_time":7.415618822},
{"learn":[0.8492045222],"iteration":456,"passed_time":6.232779539,"remaining_time":7.405687724},
{"learn":[0.8491839612],"iteration":457,"passed_time":6.24433495,"remaining_time":7.389584155},
{"learn":[0.8491209742],"iteration":458,"passed_time":6.256290705,"remaining_time":7.373972269},
{"learn":[0.8490472849],"iteration":459,"passed_time":6.268872063,"remaining_time":7.359110683},
{"learn":[0.8489827161],"iteration":460,"passed_time":6.279840352,"remaining_time":7.342372993},
{"learn":[0.848916543],"iteration":461,"passed_time":6.292395863,"remaining_time":7.327508602},
{"learn":[0.8488758049],"iteration":462,"passed_time":6.305082059,"remaining_time":7.312805758},
{"learn":[0.8488426496],"iteration":463,"passed_time":6.317720966,"remaining_time":7.298056978},
{"learn":[0.8487729667],"iteration":464,"passed_time":6.327737326,"remaining_time":7.280299934},
{"learn":[0.8487291589],"iteration":465,"passed_time":6.337158613,"remaining_time":7.261894205},
{"learn":[0.8486591973],"iteration":466,"passed_time":6.351602191,"remaining_time":7.249259032},
{"learn":[0.8485436005],"iteration":467,"passed_time":6.361991616,"remaining_time":7.232007564},
{"learn":[0.8484493708],"iteration":468,"passed_time":6.372333603,"remaining_time":7.214731649},
{"learn":[0.8484202606],"iteration":469,"passed_time":6.384157975,"remaining_time":7.199156865},
{"learn":[0.8483281441],"iteration":470,"passed_time":6.398468022,"remaining_time":7.186389774},
{"learn":[0.8482698129],"iteration":471,"passed_time":6.408918939,"remaining_time":7.169299152},
{"learn":[0.8482057407],"iteration":472,"passed_time":6.422064107,"remaining_time":7.155238445},
{"learn":[0.8481332352],"iteration":473,"passed_time":6.433143193,"remaining_time":7.13888886},
{"learn":[0.8480656863],"iteration":474,"passed_time":6.445255351,"remaining_time":7.123703283},
{"learn":[0.8480301035],"iteration":475,"passed_time":6.463031781,"remaining_time":7.114766079},
{"learn":[0.8479756212],"iteration":476,"passed_time":6.477773229,"remaining_time":7.102464148},
{"learn":[0.847893454],"iteration":477,"passed_time":6.490342836,"remaining_time":7.087780252},
{"learn":[0.8477623308],"iteration":478,"passed_time":6.506342788,"remaining_time":7.076836311},
{"learn":[0.8477459181],"iteration":479,"passed_time":6.517624526,"remaining_time":7.060759903},
{"learn":[0.8476559424],"iteration":480,"passed_time":6.532111897,"remaining_time":7.048162317},
{"learn":[0.847609624],"iteration":481,"passed_time":6.54534718,"remaining_time":7.034211284},
{"learn":[0.8475148075],"iteration":482,"passed_time":6.557988396,"remaining_time":7.01962733},
{"learn":[0.8474535617],"iteration":483,"passed_time":6.576246691,"remaining_time":7.011039861},
{"learn":[0.8473776216],"iteration":484,"passed_time":6.589797237,"remaining_time":6.997413561},
{"learn":[0.8473312458],"iteration":485,"passed_time":6.604672356,"remaining_time":6.985188459},
{"learn":[0.8472575703],"iteration":486,"passed_time":6.619304453,"remaining_time":6.972696477},
{"learn":[0.8472049426],"iteration":487,"passed_time":6.631135572,"remaining_time":6.957256994},
{"learn":[0.8471354963],"iteration":488,"passed_time":6.646017189,"remaining_time":6.945020008},
{"learn":[0.847116449],"iteration":489,"passed_time":6.657997083,"remaining_time":6.929752066},
{"learn":[0.8470645151],"iteration":490,"passed_time":6.671013379,"remaining_time":6.915571915},
{"learn":[0.8470205901],"iteration":491,"passed_time":6.685711786,"remaining_time":6.903133308},
{"learn":[0.8469704651],"iteration":492,"passed_time":6.697445653,"remaining_time":6.887636807},
{"learn":[0.8469261708],"iteration":493,"passed_time":6.708842813,"remaining_time":6.871810654},
{"learn":[0.846898797],"iteration":494,"passed_time":6.72033001,"remaining_time":6.856094253},
{"learn":[0.8468715215],"iteration":495,"passed_time":6.734492716,"remaining_time":6.843113567},
{"learn":[0.846838665],"iteration":496,"passed_time":6.748290506,"remaining_time":6.829758801},
{"learn":[0.8466121977],"iteration":497,"passed_time":6.76099705,"remaining_time":6.815302247},
{"learn":[0.8465656829],"iteration":498,"passed_time":6.774566045,"remaining_time":6.801718614},
{"learn":[0.8464816653],"iteration":499,"passed_time":6.789376532,"remaining_time":6.789376532},
{"learn":[0.8464314362],"iteration":500,"passed_time":6.804453831,"remaining_time":6.777290343},
{"learn":[0.846358673],"iteration":501,"passed_time":6.822269645,"remaining_time":6.767908931},
{"learn":[0.8462996496],"iteration":502,"passed_time":6.834709218,"remaining_time":6.753181872},
{"learn":[0.8462165501],"iteration":503,"passed_time":6.84835134,"remaining_time":6.739647351},
{"learn":[0.8460811217],"iteration":504,"passed_time":6.859191208,"remaining_time":6.723365639},
{"learn":[0.8460189491],"iteration":505,"passed_time":6.8703053,"remaining_time":6.707373158},
{"learn":[0.8459757649],"iteration":506,"passed_time":6.884503297,"remaining_time":6.694398669},
{"learn":[0.8459445531],"iteration":507,"passed_time":6.894457039,"remaining_time":6.677308786},
{"learn":[0.8458420048],"iteration":508,"passed_time":6.904614494,"remaining_time":6.660443451},
{"learn":[0.8457549093],"iteration":509,"passed_time":6.916452196,"remaining_time":6.645218777},
{"learn":[0.8457014141],"iteration":510,"passed_time":6.928937404,"remaining_time":6.630626988},
{"learn":[0.8456192336],"iteration":511,"passed_time":6.941668725,"remaining_time":6.616278004},
{"learn":[0.8455712372],"iteration":512,"passed_time":6.955224475,"remaining_time":6.602717971},
{"learn":[0.8455171639],"iteration":513,"passed_time":6.966927073,"remaining_time":6.587405754},
{"learn":[0.8454667467],"iteration":514,"passed_time":6.97817634,"remaining_time":6.571680631},
{"learn":[0.8454323207],"iteration":515,"passed_time":6.987564299,"remaining_time":6.554226978},
{"learn":[0.8453845741],"iteration":516,"passed_time":7.005563257,"remaining_time":6.544849232},
{"learn":[0.8453462744],"iteration":517,"passed_time":7.015690997,"remaining_time":6.528114016},
{"learn":[0.8453078264],"iteration":518,"passed_time":7.026563685,"remaining_time":6.512094667},
{"learn":[0.8452550945],"iteration":519,"passed_time":7.036311731,"remaining_time":6.495056982},
{"learn":[0.8452034563],"iteration":520,"passed_time":7.047962661,"remaining_time":6.479796765},
{"learn":[0.8451137769],"iteration":521,"passed_time":7.068660782,"remaining_time":6.472834969},
{"learn":[0.845012718],"iteration":522,"passed_time":7.081556661,"remaining_time":6.458704641},
{"learn":[0.8449419236],"iteration":523,"passed_time":7.095523554,"remaining_time":6.445551931},
{"learn":[0.8448774328],"iteration":524,"passed_time":7.11162115,"remaining_time":6.434323897},
{"learn":[0.8448284499],"iteration":525,"passed_time":7.125222285,"remaining_time":6.420827686},
{"learn":[0.8447722795],"iteration":526,"passed_time":7.136374058,"remaining_time":6.405132694},
{"learn":[0.844716531],"iteration":527,"passed_time":7.1466469,"remaining_time":6.388669198},
{"learn":[0.8446915801],"iteration":528,"passed_time":7.155249483,"remaining_time":6.370741979},
{"learn":[0.844649214],"iteration":529,"passed_time":7.165018599,"remaining_time":6.353884418},
{"learn":[0.8445425743],"iteration":530,"passed_time":7.183120029,"remaining_time":6.344412983},
{"learn":[0.8444851832],"iteration":531,"passed_time":7.195064222,"remaining_time":6.329492586},
{"learn":[0.8444342343],"iteration":532,"passed_time":7.206299893,"remaining_time":6.31396257},
{"learn":[0.8443687411],"iteration":533,"passed_time":7.217327722,"remaining_time":6.298267263},
{"learn":[0.8443337128],"iteration":534,"passed_time":7.22751312,"remaining_time":6.281857198},
{"learn":[0.8442928726],"iteration":535,"passed_time":7.236501118,"remaining_time":6.264433803},
{"learn":[0.8442357255],"iteration":536,"passed_time":7.247362966,"remaining_time":6.248657455},
{"learn":[0.8441843864],"iteration":537,"passed_time":7.259519117,"remaining_time":6.23401084},
{"learn":[0.8441510152],"iteration":538,"passed_time":7.268154251,"remaining_time":6.216361984},
{"learn":[0.844102867],"iteration":539,"passed_time":7.279714602,"remaining_time":6.201238365},
{"learn":[0.8440385797],"iteration":540,"passed_time":7.292951523,"remaining_time":6.187550368},
{"learn":[0.8440021708],"iteration":541,"passed_time":7.306584237,"remaining_time":6.174198488},
{"learn":[0.8439087738],"iteration":542,"passed_time":7.322552019,"remaining_time":6.162810815},
{"learn":[0.8438593106],"iteration":543,"passed_time":7.335926013,"remaining_time":6.149232099},
{"learn":[0.843818316],"iteration":544,"passed_time":7.351745136,"remaining_time":6.13769548},
{"learn":[0.8437796682],"iteration":545,"passed_time":7.365198147,"remaining_time":6.124175749},
{"learn":[0.8437242625],"iteration":546,"passed_time":7.379858162,"remaining_time":6.111655845},
{"learn":[0.8436545846],"iteration":547,"passed_time":7.393607616,"remaining_time":6.098377085},
{"learn":[0.8435849287],"iteration":548,"passed_time":7.404035589,"remaining_time":6.082368034},
{"learn":[0.8435370315],"iteration":549,"passed_time":7.414056888,"remaining_time":6.066046545},
{"learn":[0.8434771181],"iteration":550,"passed_time":7.425150732,"remaining_time":6.050621922},
{"learn":[0.8434162213],"iteration":551,"passed_time":7.43426638,"remaining_time":6.033607497},
{"learn":[0.8433856444],"iteration":552,"passed_time":7.443336321,"remaining_time":6.016584694},
{"learn":[0.8433517597],"iteration":553,"passed_time":7.452273614,"remaining_time":5.999483812},
{"learn":[0.8433210935],"iteration":554,"passed_time":7.462795033,"remaining_time":5.983682504},
{"learn":[0.8432936623],"iteration":555,"passed_time":7.472384461,"remaining_time":5.967155936},
{"learn":[0.8432216012],"iteration":556,"passed_time":7.481909813,"remaining_time":5.950603316},
{"learn":[0.8431337846],"iteration":557,"passed_time":7.492269583,"remaining_time":5.934736838},
{"learn":[0.8430997019],"iteration":558,"passed_time":7.500771597,"remaining_time":5.917424462},
{"learn":[0.8430684461],"iteration":559,"passed_time":7.509283931,"remaining_time":5.90015166},
{"learn":[0.8429886145],"iteration":560,"passed_time":7.520010475,"remaining_time":5.884642778},
{"learn":[0.8429392408],"iteration":561,"passed_time":7.529434452,"remaining_time":5.868135747},
{"learn":[0.842909833],"iteration":562,"passed_time":7.54216448,"remaining_time":5.854220032},
{"learn":[0.8428676984],"iteration":563,"passed_time":7.552635835,"remaining_time":5.838562454},
{"learn":[0.8428214059],"iteration":564,"passed_time":7.562725734,"remaining_time":5.822629547},
{"learn":[0.8427445483],"iteration":565,"passed_time":7.573542797,"remaining_time":5.807274866},
{"learn":[0.8427122516],"iteration":566,"passed_time":7.5832946,"remaining_time":5.791122684},
{"learn":[0.8426638852],"iteration":567,"passed_time":7.596342586,"remaining_time":5.777499995},
{"learn":[0.8425744291],"iteration":568,"passed_time":7.60811723,"remaining_time":5.762914808},
{"learn":[0.8424184353],"iteration":569,"passed_time":7.619701455,"remaining_time":5.748195834},
{"learn":[0.8423730084],"iteration":570,"passed_time":7.630318173,"remaining_time":5.732760939},
{"learn":[0.8423320809],"iteration":571,"passed_time":7.642317098,"remaining_time":5.718377129},
{"learn":[0.8422372539],"iteration":572,"passed_time":7.651508538,"remaining_time":5.701909504},
{"learn":[0.8422003473],"iteration":573,"passed_time":7.66334908,"remaining_time":5.68743329},
{"learn":[0.8421507509],"iteration":574,"passed_time":7.674127817,"remaining_time":5.67218143},
{"learn":[0.8421071088],"iteration":575,"passed_time":7.68324133,"remaining_time":5.655719313},
{"learn":[0.8420548546],"iteration":576,"passed_time":7.692719179,"remaining_time":5.639549762},
{"learn":[0.841825393],"iteration":577,"passed_time":7.70204424,"remaining_time":5.623291815},
{"learn":[0.8417557973],"iteration":578,"passed_time":7.712623207,"remaining_time":5.607969551},
{"learn":[0.8416968147],"iteration":579,"passed_time":7.723878534,"remaining_time":5.593153421},
{"learn":[0.8416473905],"iteration":580,"passed_time":7.733930782,"remaining_time":5.577481923},
{"learn":[0.841577148],"iteration":581,"passed_time":7.742570054,"remaining_time":5.560814918},
{"learn":[0.8414994321],"iteration":582,"passed_time":7.751294216,"remaining_time":5.544236172},
{"learn":[0.8414327565],"iteration":583,"passed_time":7.759967402,"remaining_time":5.527648013},
{"learn":[0.8413682006],"iteration":584,"passed_time":7.772108974,"remaining_time":5.513547392},
{"learn":[0.8413274496],"iteration":585,"passed_time":7.78287309,"remaining_time":5.498480306},
{"learn":[0.841264274],"iteration":586,"passed_time":7.794266356,"remaining_time":5.483870537},
{"learn":[0.8412104595],"iteration":587,"passed_time":7.803753442,"remaining_time":5.467936085},
{"learn":[0.8411608622],"iteration":588,"passed_time":7.81514207,"remaining_time":5.453350409},
{"learn":[0.841005524],"iteration":589,"passed_time":7.826464243,"remaining_time":5.438729389},
{"learn":[0.8409528754],"iteration":590,"passed_time":7.83547859,"remaining_time":5.422522408},
{"learn":[0.8408633375],"iteration":591,"passed_time":7.846323622,"remaining_time":5.407601416},
{"learn":[0.840827802],"iteration":592,"passed_time":7.85531132,"remaining_time":5.391419405},
{"learn":[0.8407782105],"iteration":593,"passed_time":7.867312514,"remaining_time":5.377321348},
{"learn":[0.8407273218],"iteration":594,"passed_time":7.877380801,"remaining_time":5.361914663},
{"learn":[0.8406648735],"iteration":595,"passed_time":7.890714433,"remaining_time":5.348739314},
{"learn":[0.840587473],"iteration":596,"passed_time":7.900164689,"remaining_time":5.332941993},
{"learn":[0.8405080208],"iteration":597,"passed_time":7.91452408,"remaining_time":5.32046602},
{"learn":[0.8404833021],"iteration":598,"passed_time":7.924523096,"remaining_time":5.305064711},
{"learn":[0.8404374055],"iteration":599,"passed_time":7.934500172,"remaining_time":5.289666782},
{"learn":[0.8403678807],"iteration":600,"passed_time":7.943708514,"remaining_time":5.273776534},
{"learn":[0.8403131311],"iteration":601,"passed_time":7.953764107,"remaining_time":5.258468629},
{"learn":[0.8402593841],"iteration":602,"passed_time":7.962799474,"remaining_time":5.242506453},
{"learn":[0.8401820703],"iteration":603,"passed_time":7.973720975,"remaining_time":5.227803818},
{"learn":[0.8401200506],"iteration":604,"passed_time":7.983479129,"remaining_time":5.212354142},
{"learn":[0.8400747405],"iteration":605,"passed_time":7.993942569,"remaining_time":5.197381802},
{"learn":[0.8400120942],"iteration":606,"passed_time":8.005871873,"remaining_time":5.183373388},
{"learn":[0.8399830292],"iteration":607,"passed_time":8.016496927,"remaining_time":5.168530913},
{"learn":[0.8399270232],"iteration":608,"passed_time":8.029476294,"remaining_time":5.155213844},
{"learn":[0.8398851505],"iteration":609,"passed_time":8.038842232,"remaining_time":5.139587656},
{"learn":[0.8398509853],"iteration":610,"passed_time":8.047908667,"remaining_time":5.123791279},
{"learn":[0.8398018894],"iteration":611,"passed_time":8.058174866,"remaining_time":5.10877753},
{"learn":[0.8397642577],"iteration":612,"passed_time":8.07130196,"remaining_time":5.095585414},
{"learn":[0.8397326602],"iteration":613,"passed_time":8.083323263,"remaining_time":5.081698338},
{"learn":[0.8397010232],"iteration":614,"passed_time":8.09420362,"remaining_time":5.067103079},
{"learn":[0.8396790829],"iteration":615,"passed_time":8.104761127,"remaining_time":5.052318624},
{"learn":[0.8396224238],"iteration":616,"passed_time":8.113888396,"remaining_time":5.036660058},
{"learn":[0.8395516213],"iteration":617,"passed_time":8.124593049,"remaining_time":5.021997645},
{"learn":[0.8395055306],"iteration":618,"passed_time":8.133603329,"remaining_time":5.006305118},
{"learn":[0.8394442922],"iteration":619,"passed_time":8.143869789,"remaining_time":4.991404064},
{"learn":[0.8393885369],"iteration":620,"passed_time":8.153509561,"remaining_time":4.976135465},
{"learn":[0.8393021195],"iteration":621,"passed_time":8.162302642,"remaining_time":4.960370416},
{"learn":[0.8392537316],"iteration":622,"passed_time":8.172376249,"remaining_time":4.945402642},
{"learn":[0.8392179118],"iteration":623,"passed_time":8.181228552,"remaining_time":4.92971464},
{"learn":[0.8391765022],"iteration":624,"passed_time":8.192811145,"remaining_time":4.915686687},
{"learn":[0.839116346],"iteration":625,"passed_time":8.202475403,"remaining_time":4.900520449},
{"learn":[0.839098995],"iteration":626,"passed_time":8.211615211,"remaining_time":4.885059767},
{"learn":[0.8390077839],"iteration":627,"passed_time":8.222084547,"remaining_time":4.87040677},
{"learn":[0.8389390718],"iteration":628,"passed_time":8.232717576,"remaining_time":4.855863626},
{"learn":[0.8389236823],"iteration":629,"passed_time":8.240977655,"remaining_time":4.839939258},
{"learn":[0.8389011806],"iteration":630,"passed_time":8.249862669,"remaining_time":4.824404635},
{"learn":[0.8388740056],"iteration":631,"passed_time":8.258896904,"remaining_time":4.808977944},
{"learn":[0.8387825401],"iteration":632,"passed_time":8.268348593,"remaining_time":4.793813481},
{"learn":[0.838680496],"iteration":633,"passed_time":8.281681834,"remaining_time":4.78090781},
{"learn":[0.8386467333],"iteration":634,"passed_time":8.291911435,"remaining_time":4.766216809},
{"learn":[0.8386088224],"iteration":635,"passed_time":8.301953743,"remaining_time":4.751432645},
{"learn":[0.8385686563],"iteration":636,"passed_time":8.314342987,"remaining_time":4.738000792},
{"learn":[0.8385256653],"iteration":637,"passed_time":8.325167029,"remaining_time":4.723684114},
{"learn":[0.8384743528],"iteration":638,"passed_time":8.337203935,"remaining_time":4.710063569},
{"learn":[0.8384063566],"iteration":639,"passed_time":8.350010577,"remaining_time":4.69688095},
{"learn":[0.8383704708],"iteration":640,"passed_time":8.360496826,"remaining_time":4.682399938},
{"learn":[0.8383104697],"iteration":641,"passed_time":8.371459738,"remaining_time":4.668197175},
{"learn":[0.8382803251],"iteration":642,"passed_time":8.381811047,"remaining_time":4.653664921},
{"learn":[0.8382209345],"iteration":643,"passed_time":8.394905607,"remaining_time":4.640662106},
{"learn":[0.8380976532],"iteration":644,"passed_time":8.405573896,"remaining_time":4.626323617},
{"learn":[0.838059278],"iteration":645,"passed_time":8.415186227,"remaining_time":4.611417839},
{"learn":[0.838011209],"iteration":646,"passed_time":8.424208368,"remaining_time":4.59620642},
{"learn":[0.8379839359],"iteration":647,"passed_time":8.432566713,"remaining_time":4.580653523},
{"learn":[0.837938962],"iteration":648,"passed_time":8.441688452,"remaining_time":4.565535665},
{"learn":[0.8379019016],"iteration":649,"passed_time":8.450767631,"remaining_time":4.55041334},
{"learn":[0.8378453214],"iteration":650,"passed_time":8.460514634,"remaining_time":4.5356676},
{"learn":[0.8378185137],"iteration":651,"passed_time":8.47021467,"remaining_time":4.520912125},
{"learn":[0.837780393],"iteration":652,"passed_time":8.480188731,"remaining_time":4.506317748},
{"learn":[0.8377346435],"iteration":653,"passed_time":8.489878847,"remaining_time":4.49158728},
{"learn":[0.837658439],"iteration":654,"passed_time":8.499880739,"remaining_time":4.47703642},
{"learn":[0.8375992009],"iteration":655,"passed_time":8.509378034,"remaining_time":4.462234823},
{"learn":[0.8375467359],"iteration":656,"passed_time":8.519458545,"remaining_time":4.447753852},
{"learn":[0.8375023997],"iteration":657,"passed_time":8.529855019,"remaining_time":4.433450481},
{"learn":[0.8374292772],"iteration":658,"passed_time":8.539807398,"remaining_time":4.418929169},
{"learn":[0.8372764221],"iteration":659,"passed_time":8.550593624,"remaining_time":4.404851261},
{"learn":[0.8372218978],"iteration":660,"passed_time":8.562088377,"remaining_time":4.391146687},
{"learn":[0.8371988319],"iteration":661,"passed_time":8.575133622,"remaining_time":4.37824043},
{"learn":[0.8371726817],"iteration":662,"passed_time":8.587200586,"remaining_time":4.364836497},
{"learn":[0.8371352383],"iteration":663,"passed_time":8.598332571,"remaining_time":4.35096347},
{"learn":[0.8370929714],"iteration":664,"passed_time":8.60862191,"remaining_time":4.336674195},
{"learn":[0.8370759432],"iteration":665,"passed_time":8.61799756,"remaining_time":4.321938716},
{"learn":[0.8370054881],"iteration":666,"passed_time":8.6274974,"remaining_time":4.307281311},
{"learn":[0.8369756364],"iteration":667,"passed_time":8.637046942,"remaining_time":4.292664049},
{"learn":[0.8369156689],"iteration":668,"passed_time":8.647016209,"remaining_time":4.278269604},
{"learn":[0.8368806894],"iteration":669,"passed_time":8.655739519,"remaining_time":4.263274689},
{"learn":[0.8368070556],"iteration":670,"passed_time":8.665852635,"remaining_time":4.248979906},
{"learn":[0.8367684409],"iteration":671,"passed_time":8.675034247,"remaining_time":4.234242906},
{"learn":[0.8367237944],"iteration":672,"passed_time":8.685365418,"remaining_time":4.220080968},
{"learn":[0.8367144384],"iteration":673,"passed_time":8.693894694,"remaining_time":4.205058858},
{"learn":[0.8366682271],"iteration":674,"passed_time":8.704466958,"remaining_time":4.191039646},
{"learn":[0.8365740641],"iteration":675,"passed_time":8.714116338,"remaining_time":4.176588304},
{"learn":[0.8364805314],"iteration":676,"passed_time":8.723610426,"remaining_time":4.162077057},
{"learn":[0.8364068496],"iteration":677,"passed_time":8.736896199,"remaining_time":4.149381381},
{"learn":[0.8363555025],"iteration":678,"passed_time":8.746993491,"remaining_time":4.135176599},
{"learn":[0.836322926],"iteration":679,"passed_time":8.756661767,"remaining_time":4.120782008},
{"learn":[0.836269939],"iteration":680,"passed_time":8.765931084,"remaining_time":4.106214414},
{"learn":[0.8362235372],"iteration":681,"passed_time":8.775105811,"remaining_time":4.091618252},
{"learn":[0.8361522799],"iteration":682,"passed_time":8.784840171,"remaining_time":4.077297708},
{"learn":[0.8360936551],"iteration":683,"passed_time":8.796678945,"remaining_time":4.063962788},
{"learn":[0.8360606912],"iteration":684,"passed_time":8.805546657,"remaining_time":4.049265981},
{"learn":[0.8360244704],"iteration":685,"passed_time":8.814024426,"remaining_time":4.034407682},
{"learn":[0.8359735328],"iteration":686,"passed_time":8.82418672,"remaining_time":4.020335434},
{"learn":[0.8359376789],"iteration":687,"passed_time":8.832993257,"remaining_time":4.005659733},
{"learn":[0.835875871],"iteration":688,"passed_time":8.842289293,"remaining_time":3.991222018},
{"learn":[0.8358459046],"iteration":689,"passed_time":8.851117731,"remaining_time":3.976589126},
{"learn":[0.8357571363],"iteration":690,"passed_time":8.861854344,"remaining_time":3.962826328},
{"learn":[0.8356794965],"iteration":691,"passed_time":8.872449908,"remaining_time":3.949009496},
{"learn":[0.8356223193],"iteration":692,"passed_time":8.883320903,"remaining_time":3.935323979},
{"learn":[0.8355934169],"iteration":693,"passed_time":8.894475091,"remaining_time":3.921771438},
{"learn":[0.8355304906],"iteration":694,"passed_time":8.905211197,"remaining_time":3.908042324},
{"learn":[0.8354985256],"iteration":695,"passed_time":8.917100286,"remaining_time":3.894825412},
{"learn":[0.8354497612],"iteration":696,"passed_time":8.928951092,"remaining_time":3.881595669},
{"learn":[0.8354018305],"iteration":697,"passed_time":8.93931212,"remaining_time":3.867725301},
{"learn":[0.8353324162],"iteration":698,"passed_time":8.948792814,"remaining_time":3.85348589},
{"learn":[0.8352981482],"iteration":699,"passed_time":8.959603877,"remaining_time":3.839830233},
{"learn":[0.8352365346],"iteration":700,"passed_time":8.971326021,"remaining_time":3.826571298},
{"learn":[0.8351665701],"iteration":701,"passed_time":8.981797827,"remaining_time":3.812785972},
{"learn":[0.8351257439],"iteration":702,"passed_time":8.992129098,"remaining_time":3.7989507},
{"learn":[0.8350747322],"iteration":703,"passed_time":9.000770354,"remaining_time":3.784414808},
{"learn":[0.8349949178],"iteration":704,"passed_time":9.011129818,"remaining_time":3.770614605},
{"learn":[0.8349326987],"iteration":705,"passed_time":9.02228311,"remaining_time":3.757154723},
{"learn":[0.8348931178],"iteration":706,"passed_time":9.032367939,"remaining_time":3.743258566},
{"learn":[0.8348173996],"iteration":707,"passed_time":9.04258476,"remaining_time":3.729427613},
{"learn":[0.8347883157],"iteration":708,"passed_time":9.051895153,"remaining_time":3.715234823},
{"learn":[0.8347318393],"iteration":709,"passed_time":9.067643693,"remaining_time":3.703685452},
{"learn":[0.8346761545],"iteration":710,"passed_time":9.079689786,"remaining_time":3.690619336},
{"learn":[0.8346041084],"iteration":711,"passed_time":9.090406712,"remaining_time":3.677018445},
{"learn":[0.8345598075],"iteration":712,"passed_time":9.100568405,"remaining_time":3.663202149},
{"learn":[0.8345429608],"iteration":713,"passed_time":9.108840668,"remaining_time":3.648639259},
{"learn":[0.8345081318],"iteration":714,"passed_time":9.117822354,"remaining_time":3.634376742},
{"learn":[0.8344536922],"iteration":715,"passed_time":9.128168193,"remaining_time":3.620670065},
{"learn":[0.8343895138],"iteration":716,"passed_time":9.136624301,"remaining_time":3.606226886},
{"learn":[0.8343039976],"iteration":717,"passed_time":9.147727954,"remaining_time":3.592840227},
{"learn":[0.8342436392],"iteration":718,"passed_time":9.158390277,"remaining_time":3.579287438},
{"learn":[0.8341979009],"iteration":719,"passed_time":9.168226118,"remaining_time":3.565421268},
{"learn":[0.8341428901],"iteration":720,"passed_time":9.178395745,"remaining_time":3.551695441},
{"learn":[0.8341103307],"iteration":721,"passed_time":9.186071858,"remaining_time":3.537019358},
{"learn":[0.8340408643],"iteration":722,"passed_time":9.197152278,"remaining_time":3.523666917},
{"learn":[0.8339858298],"iteration":723,"passed_time":9.206405553,"remaining_time":3.509624216},
{"learn":[0.8339446611],"iteration":724,"passed_time":9.216435028,"remaining_time":3.495889148},
{"learn":[0.833892957],"iteration":725,"passed_time":9.228259966,"remaining_time":3.482841915},
{"learn":[0.8338634216],"iteration":726,"passed_time":9.237992442,"remaining_time":3.469012293},
{"learn":[0.8338208914],"iteration":727,"passed_time":9.249664814,"remaining_time":3.455918722},
{"learn":[0.8337583207],"iteration":728,"passed_time":9.260618054,"remaining_time":3.442561718},
{"learn":[0.8337277115],"iteration":729,"passed_time":9.27073397,"remaining_time":3.428901605},
{"learn":[0.8336781652],"iteration":730,"passed_time":9.281789943,"remaining_time":3.41559712},
{"learn":[0.8336555799],"iteration":731,"passed_time":9.290210815,"remaining_time":3.401334014},
{"learn":[0.8336133606],"iteration":732,"passed_time":9.299205967,"remaining_time":3.387296034},
{"learn":[0.8335364642],"iteration":733,"passed_time":9.309952178,"remaining_time":3.373906375},
{"learn":[0.8334898761],"iteration":734,"passed_time":9.321234206,"remaining_time":3.360717095},
{"learn":[0.8334707336],"iteration":735,"passed_time":9.329902763,"remaining_time":3.346595556},
{"learn":[0.8334513147],"iteration":736,"passed_time":9.338617908,"remaining_time":3.332505441},
{"learn":[0.8333991472],"iteration":737,"passed_time":9.347503473,"remaining_time":3.318490393},
{"learn":[0.833334466],"iteration":738,"passed_time":9.35745436,"remaining_time":3.304865478},
{"learn":[0.8332996063],"iteration":739,"passed_time":9.365514204,"remaining_time":3.290586072},
{"learn":[0.8332582872],"iteration":740,"passed_time":9.374729498,"remaining_time":3.276727314},
{"learn":[0.8332120579],"iteration":741,"passed_time":9.384242703,"remaining_time":3.262984659},
{"learn":[0.833163263],"iteration":742,"passed_time":9.394001018,"remaining_time":3.249338172},
{"learn":[0.8331123505],"iteration":743,"passed_time":9.402508913,"remaining_time":3.235271884},
{"learn":[0.8330712002],"iteration":744,"passed_time":9.412661148,"remaining_time":3.221783346},
{"learn":[0.833016235],"iteration":745,"passed_time":9.421557914,"remaining_time":3.207876287},
{"learn":[0.8329871378],"iteration":746,"passed_time":9.429866495,"remaining_time":3.193783432},
{"learn":[0.8329388506],"iteration":747,"passed_time":9.441623806,"remaining_time":3.180867913},
{"learn":[0.8328801674],"iteration":748,"passed_time":9.452301589,"remaining_time":3.167593723},
{"learn":[0.8327847011],"iteration":749,"passed_time":9.463074741,"remaining_time":3.154358247},
{"learn":[0.832764201],"iteration":750,"passed_time":9.471801998,"remaining_time":3.140450995},
{"learn":[0.8327143915],"iteration":751,"passed_time":9.481609897,"remaining_time":3.126913902},
{"learn":[0.8326597831],"iteration":752,"passed_time":9.491662605,"remaining_time":3.113467016},
{"learn":[0.832591201],"iteration":753,"passed_time":9.501181229,"remaining_time":3.099854884},
{"learn":[0.8325537103],"iteration":754,"passed_time":9.511083365,"remaining_time":3.086378045},
{"learn":[0.8324858822],"iteration":755,"passed_time":9.522073093,"remaining_time":3.073261686},
{"learn":[0.8324225515],"iteration":756,"passed_time":9.531714919,"remaining_time":3.059718263},
{"learn":[0.8323432722],"iteration":757,"passed_time":9.541166298,"remaining_time":3.046124333},
{"learn":[0.8323153538],"iteration":758,"passed_time":9.549974988,"remaining_time":3.032337249},
{"learn":[0.8322650804],"iteration":759,"passed_time":9.559779911,"remaining_time":3.018877866},
{"learn":[0.8322305519],"iteration":760,"passed_time":9.569014882,"remaining_time":3.005249089},
{"learn":[0.8321992213],"iteration":761,"passed_time":9.578185704,"remaining_time":2.991611808},
{"learn":[0.8321610002],"iteration":762,"passed_time":9.587937837,"remaining_time":2.978166799},
{"learn":[0.8321321669],"iteration":763,"passed_time":9.59822203,"remaining_time":2.96489581},
{"learn":[0.8320874598],"iteration":764,"passed_time":9.606981528,"remaining_time":2.95116426},
{"learn":[0.8320028558],"iteration":765,"passed_time":9.618000492,"remaining_time":2.93813592},
{"learn":[0.8319610764],"iteration":766,"passed_time":9.631302841,"remaining_time":2.925806469},
{"learn":[0.8319387889],"iteration":767,"passed_time":9.640284206,"remaining_time":2.912169187},
{"learn":[0.8318624979],"iteration":768,"passed_time":9.650021331,"remaining_time":2.898771037},
{"learn":[0.8317703361],"iteration":769,"passed_time":9.660594147,"remaining_time":2.885632018},
{"learn":[0.831713456],"iteration":770,"passed_time":9.671334281,"remaining_time":2.872549352},
{"learn":[0.8316611094],"iteration":771,"passed_time":9.681613114,"remaining_time":2.859336515},
{"learn":[0.8315997526],"iteration":772,"passed_time":9.694786264,"remaining_time":2.846981219},
{"learn":[0.8315267095],"iteration":773,"passed_time":9.7048111,"remaining_time":2.833704533},
{"learn":[0.8314969831],"iteration":774,"passed_time":9.713951494,"remaining_time":2.820179466},
{"learn":[0.831419837],"iteration":775,"passed_time":9.724064405,"remaining_time":2.806946426},
{"learn":[0.8313930887],"iteration":776,"passed_time":9.732561611,"remaining_time":2.793257708},
{"learn":[0.8313257259],"iteration":777,"passed_time":9.741669984,"remaining_time":2.779756731},
{"learn":[0.831222433],"iteration":778,"passed_time":9.75097103,"remaining_time":2.766321691},
{"learn":[0.8311942817],"iteration":779,"passed_time":9.759087811,"remaining_time":2.752563229},
{"learn":[0.8311405962],"iteration":780,"passed_time":9.769397231,"remaining_time":2.739434051},
{"learn":[0.831100397],"iteration":781,"passed_time":9.777786434,"remaining_time":2.725776781},
{"learn":[0.8310645447],"iteration":782,"passed_time":9.786635571,"remaining_time":2.712260433},
{"learn":[0.831009145],"iteration":783,"passed_time":9.795534551,"remaining_time":2.698769723},
{"learn":[0.8309336727],"iteration":784,"passed_time":9.804483946,"remaining_time":2.68530452},
{"learn":[0.8308797156],"iteration":785,"passed_time":9.813694352,"remaining_time":2.671921872},
{"learn":[0.8308165698],"iteration":786,"passed_time":9.823433741,"remaining_time":2.658692995},
{"learn":[0.8307686019],"iteration":787,"passed_time":9.832104082,"remaining_time":2.645185362},
{"learn":[0.8307192371],"iteration":788,"passed_time":9.842076659,"remaining_time":2.632038245},
{"learn":[0.8306615087],"iteration":789,"passed_time":9.851665465,"remaining_time":2.618797149},
{"learn":[0.8306332486],"iteration":790,"passed_time":9.861450691,"remaining_time":2.605617186},
{"learn":[0.8306137889],"iteration":791,"passed_time":9.870486218,"remaining_time":2.592248906},
{"learn":[0.8305631566],"iteration":792,"passed_time":9.879696413,"remaining_time":2.578937147},
{"learn":[0.8304972604],"iteration":793,"passed_time":9.889868125,"remaining_time":2.565885181},
{"learn":[0.8304562082],"iteration":794,"passed_time":9.900545266,"remaining_time":2.552970792},
{"learn":[0.8303888771],"iteration":795,"passed_time":9.910076264,"remaining_time":2.539768289},
{"learn":[0.8303562212],"iteration":796,"passed_time":9.92002658,"remaining_time":2.526681802},
{"learn":[0.8303110182],"iteration":797,"passed_time":9.930576302,"remaining_time":2.513754903},
{"learn":[0.8302656725],"iteration":798,"passed_time":9.944454107,"remaining_time":2.501671183},
{"learn":[0.8302057048],"iteration":799,"passed_time":9.953374197,"remaining_time":2.488343549},
{"learn":[0.8301711178],"iteration":800,"passed_time":9.965404721,"remaining_time":2.475799675},
{"learn":[0.8301107994],"iteration":801,"passed_time":9.975930699,"remaining_time":2.462885634},
{"learn":[0.8300875252],"iteration":802,"passed_time":9.985824017,"remaining_time":2.44982233},
{"learn":[0.8300576708],"iteration":803,"passed_time":9.994624783,"remaining_time":2.436500569},
{"learn":[0.8300257682],"iteration":804,"passed_time":10.00480643,"remaining_time":2.42352454},
{"learn":[0.8299708259],"iteration":805,"passed_time":10.01480756,"remaining_time":2.410511993},
{"learn":[0.8299047644],"iteration":806,"passed_time":10.02595307,"remaining_time":2.397780597},
{"learn":[0.8298829558],"iteration":807,"passed_time":10.03465865,"remaining_time":2.384473343},
{"learn":[0.8298398274],"iteration":808,"passed_time":10.04360726,"remaining_time":2.37123484},
{"learn":[0.8298185793],"iteration":809,"passed_time":10.05086074,"remaining_time":2.35760931},
{"learn":[0.8297758396],"iteration":810,"passed_time":10.06292577,"remaining_time":2.345120803},
{"learn":[0.8297438835],"iteration":811,"passed_time":10.07365022,"remaining_time":2.332322958},
{"learn":[0.8297114636],"iteration":812,"passed_time":10.08133466,"remaining_time":2.318830974},
{"learn":[0.8296865837],"iteration":813,"passed_time":10.09049044,"remaining_time":2.305689461},
{"learn":[0.8296481554],"iteration":814,"passed_time":10.09978555,"remaining_time":2.292589358},
{"learn":[0.8296156308],"iteration":815,"passed_time":10.10954251,"remaining_time":2.279602722},
{"learn":[0.8295461056],"iteration":816,"passed_time":10.12046479,"remaining_time":2.266885014},
{"learn":[0.8294831767],"iteration":817,"passed_time":10.13157942,"remaining_time":2.254214491},
{"learn":[0.8294340681],"iteration":818,"passed_time":10.14244714,"remaining_time":2.241493202},
{"learn":[0.8293859649],"iteration":819,"passed_time":10.15338545,"remaining_time":2.228791928},
{"learn":[0.8293552341],"iteration":820,"passed_time":10.16533871,"remaining_time":2.216316235},
{"learn":[0.8293041301],"iteration":821,"passed_time":10.17710911,"remaining_time":2.203802217},
{"learn":[0.8292732456],"iteration":822,"passed_time":10.18945279,"remaining_time":2.191413297},
{"learn":[0.8292148326],"iteration":823,"passed_time":10.20530757,"remaining_time":2.179774432},
{"learn":[0.8291822686],"iteration":824,"passed_time":10.21889178,"remaining_time":2.167643711},
{"learn":[0.8290810128],"iteration":825,"passed_time":10.23082132,"remaining_time":2.155160908},
{"learn":[0.8290379891],"iteration":826,"passed_time":10.24369446,"remaining_time":2.142876834},
{"learn":[0.8289670885],"iteration":827,"passed_time":10.25784858,"remaining_time":2.130857434},
{"learn":[0.8289268536],"iteration":828,"passed_time":10.26798802,"remaining_time":2.118004766},
{"learn":[0.828907853],"iteration":829,"passed_time":10.27964432,"remaining_time":2.105469318},
{"learn":[0.8288127022],"iteration":830,"passed_time":10.2941728,"remaining_time":2.093520099},
{"learn":[0.8287593954],"iteration":831,"passed_time":10.30972857,"remaining_time":2.081772116},
{"learn":[0.8287361832],"iteration":832,"passed_time":10.32793476,"remaining_time":2.070546345},
{"learn":[0.8287192263],"iteration":833,"passed_time":10.33806722,"remaining_time":2.057696833},
{"learn":[0.828680882],"iteration":834,"passed_time":10.3474833,"remaining_time":2.044712269},
{"learn":[0.8286535401],"iteration":835,"passed_time":10.36144707,"remaining_time":2.032628372},
{"learn":[0.8286158229],"iteration":836,"passed_time":10.37350751,"remaining_time":2.020169324},
{"learn":[0.8285869442],"iteration":837,"passed_time":10.38705095,"remaining_time":2.007997917},
{"learn":[0.8285469128],"iteration":838,"passed_time":10.39911725,"remaining_time":1.995539782},
{"learn":[0.828514408],"iteration":839,"passed_time":10.40974578,"remaining_time":1.982808719},
{"learn":[0.8284761206],"iteration":840,"passed_time":10.41853336,"remaining_time":1.969734606},
{"learn":[0.8284393067],"iteration":841,"passed_time":10.42838662,"remaining_time":1.956870649},
{"learn":[0.8283816171],"iteration":842,"passed_time":10.43807531,"remaining_time":1.943983183},
{"learn":[0.8283113622],"iteration":843,"passed_time":10.44830652,"remaining_time":1.931203575},
{"learn":[0.8282695295],"iteration":844,"passed_time":10.45789176,"remaining_time":1.918311507},
{"learn":[0.8281850743],"iteration":845,"passed_time":10.46718649,"remaining_time":1.905374373},
{"learn":[0.8281262641],"iteration":846,"passed_time":10.47637908,"remaining_time":1.892427391},
{"learn":[0.8280753925],"iteration":847,"passed_time":10.48677758,"remaining_time":1.879705416},
{"learn":[0.8280262684],"iteration":848,"passed_time":10.49802495,"remaining_time":1.86713989},
{"learn":[0.8279876122],"iteration":849,"passed_time":10.5073991,"remaining_time":1.8542469},
{"learn":[0.827925051],"iteration":850,"passed_time":10.51871312,"remaining_time":1.841701826},
{"learn":[0.8278657925],"iteration":851,"passed_time":10.52848024,"remaining_time":1.828890934},
{"learn":[0.8278230614],"iteration":852,"passed_time":10.53968868,"remaining_time":1.816335563},
{"learn":[0.8277527529],"iteration":853,"passed_time":10.55361201,"remaining_time":1.804247486},
{"learn":[0.8276883105],"iteration":854,"passed_time":10.56493421,"remaining_time":1.791713989},
{"learn":[0.8276555414],"iteration":855,"passed_time":10.57370957,"remaining_time":1.778754881},
{"learn":[0.8275964167],"iteration":856,"passed_time":10.58368291,"remaining_time":1.766005433},
{"learn":[0.8275324203],"iteration":857,"passed_time":10.5939711,"remaining_time":1.753314564},
{"learn":[0.8274818575],"iteration":858,"passed_time":10.60397197,"remaining_time":1.740582128},
{"learn":[0.8274367378],"iteration":859,"passed_time":10.61475119,"remaining_time":1.727982752},
{"learn":[0.827399383],"iteration":860,"passed_time":10.62332603,"remaining_time":1.715031729},
{"learn":[0.8273756964],"iteration":861,"passed_time":10.63267447,"remaining_time":1.702214706},
{"learn":[0.8273383941],"iteration":862,"passed_time":10.64257999,"remaining_time":1.689494158},
{"learn":[0.8272855446],"iteration":863,"passed_time":10.65153102,"remaining_time":1.676629882},
{"learn":[0.8272473563],"iteration":864,"passed_time":10.6603136,"remaining_time":1.663748365},
{"learn":[0.8272002552],"iteration":865,"passed_time":10.67144716,"remaining_time":1.651240092},
{"learn":[0.8271501722],"iteration":866,"passed_time":10.68249496,"remaining_time":1.638721833},
{"learn":[0.8271087281],"iteration":867,"passed_time":10.69071075,"remaining_time":1.62577629},
{"learn":[0.8270634665],"iteration":868,"passed_time":10.69899286,"remaining_time":1.612851629},
{"learn":[0.8270309362],"iteration":869,"passed_time":10.70758253,"remaining_time":1.599983597},
{"learn":[0.8269687591],"iteration":870,"passed_time":10.71749632,"remaining_time":1.587321499},
{"learn":[0.8269259586],"iteration":871,"passed_time":10.72669708,"remaining_time":1.574561039},
{"learn":[0.8268656169],"iteration":872,"passed_time":10.73693825,"remaining_time":1.561960088},
{"learn":[0.826838383],"iteration":873,"passed_time":10.74594329,"remaining_time":1.549186332},
{"learn":[0.826760422],"iteration":874,"passed_time":10.75642647,"remaining_time":1.536632352},
{"learn":[0.8267149872],"iteration":875,"passed_time":10.76705259,"remaining_time":1.524103335},
{"learn":[0.826648248],"iteration":876,"passed_time":10.77803096,"remaining_time":1.511628059},
{"learn":[0.8266067783],"iteration":877,"passed_time":10.78997482,"remaining_time":1.499290351},
{"learn":[0.8265795333],"iteration":878,"passed_time":10.79906002,"remaining_time":1.486560026},
{"learn":[0.8265670254],"iteration":879,"passed_time":10.80740962,"remaining_time":1.473737675},
{"learn":[0.8264948271],"iteration":880,"passed_time":10.81702809,"remaining_time":1.461096871},
{"learn":[0.8264325982],"iteration":881,"passed_time":10.82611566,"remaining_time":1.448391891},
{"learn":[0.8263737158],"iteration":882,"passed_time":10.83737597,"remaining_time":1.435983},
{"learn":[0.8263500204],"iteration":883,"passed_time":10.84671716,"remaining_time":1.423324876},
{"learn":[0.8263211548],"iteration":884,"passed_time":10.85798822,"remaining_time":1.410925023},
{"learn":[0.8262633052],"iteration":885,"passed_time":10.86943898,"remaining_time":1.398550839},
{"learn":[0.8262119934],"iteration":886,"passed_time":10.87946197,"remaining_time":1.385996846},
{"learn":[0.8261339828],"iteration":887,"passed_time":10.8893447,"remaining_time":1.373430863},
{"learn":[0.8260862757],"iteration":888,"passed_time":10.8995015,"remaining_time":1.360905137},
{"learn":[0.8260569622],"iteration":889,"passed_time":10.90966111,"remaining_time":1.348385081},
{"learn":[0.8260060556],"iteration":890,"passed_time":10.92107153,"remaining_time":1.336023341},
{"learn":[0.8259738457],"iteration":891,"passed_time":10.93346218,"remaining_time":1.323782416},
{"learn":[0.8259067413],"iteration":892,"passed_time":10.94255403,"remaining_time":1.311145892},
{"learn":[0.8258716305],"iteration":893,"passed_time":10.95530246,"remaining_time":1.298950851},
{"learn":[0.8258368936],"iteration":894,"passed_time":10.96390446,"remaining_time":1.286268121},
{"learn":[0.8257963671],"iteration":895,"passed_time":10.97434159,"remaining_time":1.273807506},
{"learn":[0.8257488722],"iteration":896,"passed_time":10.98258607,"remaining_time":1.261099627},
{"learn":[0.8257001098],"iteration":897,"passed_time":10.99321199,"remaining_time":1.248672186},
{"learn":[0.8256589856],"iteration":898,"passed_time":11.00422997,"remaining_time":1.2362928},
{"learn":[0.8256186844],"iteration":899,"passed_time":11.01618378,"remaining_time":1.22402042},
{"learn":[0.8255952554],"iteration":900,"passed_time":11.02511595,"remaining_time":1.211416736},
{"learn":[0.8255479403],"iteration":901,"passed_time":11.03522372,"remaining_time":1.198948919},
{"learn":[0.8255074641],"iteration":902,"passed_time":11.04637726,"remaining_time":1.186598664},
{"learn":[0.825477103],"iteration":903,"passed_time":11.05810499,"remaining_time":1.174312035},
{"learn":[0.8253981666],"iteration":904,"passed_time":11.06869526,"remaining_time":1.161907237},
{"learn":[0.8253422929],"iteration":905,"passed_time":11.07842714,"remaining_time":1.149417385},
{"learn":[0.8252934931],"iteration":906,"passed_time":11.08800449,"remaining_time":1.13691777},
{"learn":[0.8252153358],"iteration":907,"passed_time":11.09728419,"remaining_time":1.124394433},
{"learn":[0.8251524598],"iteration":908,"passed_time":11.10758085,"remaining_time":1.111980041},
{"learn":[0.8251097319],"iteration":909,"passed_time":11.11749292,"remaining_time":1.099532267},
{"learn":[0.8250588589],"iteration":910,"passed_time":11.12824748,"remaining_time":1.087172367},
{"learn":[0.8250130716],"iteration":911,"passed_time":11.13839896,"remaining_time":1.074757794},
{"learn":[0.8249827112],"iteration":912,"passed_time":11.14779563,"remaining_time":1.062276254},
{"learn":[0.8249039406],"iteration":913,"passed_time":11.15870546,"remaining_time":1.04994384},
{"learn":[0.8248511616],"iteration":914,"passed_time":11.16828683,"remaining_time":1.037491127},
{"learn":[0.8248290518],"iteration":915,"passed_time":11.17973019,"remaining_time":1.025215433},
{"learn":[0.8247973081],"iteration":916,"passed_time":11.18929417,"remaining_time":1.012771447},
{"learn":[0.8247420147],"iteration":917,"passed_time":11.1987523,"remaining_time":1.000324279},
{"learn":[0.8247031123],"iteration":918,"passed_time":11.20860654,"remaining_time":0.9879185308},
{"learn":[0.8246770619],"iteration":919,"passed_time":11.21805804,"remaining_time":0.9754833078},
{"learn":[0.8246277182],"iteration":920,"passed_time":11.22819234,"remaining_time":0.9631131324},
{"learn":[0.8245856596],"iteration":921,"passed_time":11.23792146,"remaining_time":0.9507135292},
{"learn":[0.8245548232],"iteration":922,"passed_time":11.24999612,"remaining_time":0.9385153858},
{"learn":[0.8245254464],"iteration":923,"passed_time":11.25940346,"remaining_time":0.9260981204},
{"learn":[0.8244830892],"iteration":924,"passed_time":11.26843377,"remaining_time":0.9136567922},
{"learn":[0.8244304148],"iteration":925,"passed_time":11.27772135,"remaining_time":0.901243391},
{"learn":[0.8243729823],"iteration":926,"passed_time":11.28707961,"remaining_time":0.888842299},
{"learn":[0.8243504512],"iteration":927,"passed_time":11.2970432,"remaining_time":0.8764947307},
{"learn":[0.8242785759],"iteration":928,"passed_time":11.30580223,"remaining_time":0.8640602353},
{"learn":[0.824241012],"iteration":929,"passed_time":11.31596749,"remaining_time":0.8517394887},
{"learn":[0.8242041286],"iteration":930,"passed_time":11.32670988,"remaining_time":0.8394661455},
{"learn":[0.8241347224],"iteration":931,"passed_time":11.33752827,"remaining_time":0.8272016337},
{"learn":[0.8240773908],"iteration":932,"passed_time":11.34830109,"remaining_time":0.8149369489},
{"learn":[0.8240269414],"iteration":933,"passed_time":11.35763986,"remaining_time":0.8025741229},
{"learn":[0.8239947298],"iteration":934,"passed_time":11.36735537,"remaining_time":0.7902439559},
{"learn":[0.8239720911],"iteration":935,"passed_time":11.37619506,"remaining_time":0.7778594916},
{"learn":[0.8238960833],"iteration":936,"passed_time":11.38587527,"remaining_time":0.7655391058},
{"learn":[0.8238654175],"iteration":937,"passed_time":11.39453533,"remaining_time":0.7531569197},
{"learn":[0.8238020624],"iteration":938,"passed_time":11.40435137,"remaining_time":0.7408577565},
{"learn":[0.8237150402],"iteration":939,"passed_time":11.41400367,"remaining_time":0.7285534259},
{"learn":[0.823692515],"iteration":940,"passed_time":11.42212347,"remaining_time":0.7161586447},
{"learn":[0.8236711186],"iteration":941,"passed_time":11.43256655,"remaining_time":0.7039159872},
{"learn":[0.8236111907],"iteration":942,"passed_time":11.44523512,"remaining_time":0.6918116671},
{"learn":[0.8235804163],"iteration":943,"passed_time":11.45715773,"remaining_time":0.679661899},
{"learn":[0.8235134027],"iteration":944,"passed_time":11.47058619,"remaining_time":0.6676002542},
{"learn":[0.8234607639],"iteration":945,"passed_time":11.48621811,"remaining_time":0.6556614987},
{"learn":[0.8234017462],"iteration":946,"passed_time":11.50146877,"remaining_time":0.643693606},
{"learn":[0.8233633542],"iteration":947,"passed_time":11.51779706,"remaining_time":0.6317778979},
{"learn":[0.8233380146],"iteration":948,"passed_time":11.5364271,"remaining_time":0.6199765884},
{"learn":[0.8233046794],"iteration":949,"passed_time":11.55838757,"remaining_time":0.6083361878},
{"learn":[0.8232698998],"iteration":950,"passed_time":11.5741798,"remaining_time":0.5963562672},
{"learn":[0.8232372659],"iteration":951,"passed_time":11.58755885,"remaining_time":0.5842466646},
{"learn":[0.8231726463],"iteration":952,"passed_time":11.60553051,"remaining_time":0.5723608963},
{"learn":[0.82310613],"iteration":953,"passed_time":11.61902795,"remaining_time":0.5602466309},
{"learn":[0.8230625288],"iteration":954,"passed_time":11.63280507,"remaining_time":0.5481426473},
{"learn":[0.8230270568],"iteration":955,"passed_time":11.64468762,"remaining_time":0.5359479656},
{"learn":[0.8229810884],"iteration":956,"passed_time":11.65447507,"remaining_time":0.5236597992},
{"learn":[0.8229117037],"iteration":957,"passed_time":11.66536407,"remaining_time":0.5114251469},
{"learn":[0.8228746765],"iteration":958,"passed_time":11.67853758,"remaining_time":0.4992909705},
{"learn":[0.822855618],"iteration":959,"passed_time":11.6884868,"remaining_time":0.4870202834},
{"learn":[0.8228211776],"iteration":960,"passed_time":11.69891007,"remaining_time":0.4747736655},
{"learn":[0.8227697989],"iteration":961,"passed_time":11.70925648,"remaining_time":0.4625278026},
{"learn":[0.8227284697],"iteration":962,"passed_time":11.71978104,"remaining_time":0.4502927295},
{"learn":[0.8226547487],"iteration":963,"passed_time":11.73148364,"remaining_time":0.4381051981},
{"learn":[0.8225933926],"iteration":964,"passed_time":11.74165661,"remaining_time":0.4258631932},
{"learn":[0.8225271033],"iteration":965,"passed_time":11.75153403,"remaining_time":0.4136150694},
{"learn":[0.8225063369],"iteration":966,"passed_time":11.7602383,"remaining_time":0.4013318136},
{"learn":[0.8224668562],"iteration":967,"passed_time":11.77008881,"remaining_time":0.3890938451},
{"learn":[0.8224444833],"iteration":968,"passed_time":11.7790827,"remaining_time":0.3768333991},
{"learn":[0.822243427],"iteration":969,"passed_time":11.79093492,"remaining_time":0.3646680904},
{"learn":[0.8222060194],"iteration":970,"passed_time":11.80029157,"remaining_time":0.3524288935},
{"learn":[0.8221628905],"iteration":971,"passed_time":11.81048958,"remaining_time":0.3402198645},
{"learn":[0.8221250301],"iteration":972,"passed_time":11.81926523,"remaining_time":0.3279754997},
{"learn":[0.8220879614],"iteration":973,"passed_time":11.82998047,"remaining_time":0.3157900332},
{"learn":[0.8220532541],"iteration":974,"passed_time":11.84089249,"remaining_time":0.303612628},
{"learn":[0.822012072],"iteration":975,"passed_time":11.85311449,"remaining_time":0.2914700285},
{"learn":[0.8219505691],"iteration":976,"passed_time":11.86625424,"remaining_time":0.2793488715},
{"learn":[0.8219195521],"iteration":977,"passed_time":11.88025604,"remaining_time":0.2672450233},
{"learn":[0.8218776685],"iteration":978,"passed_time":11.89214058,"remaining_time":0.2550918816},
{"learn":[0.8218473301],"iteration":979,"passed_time":11.90853482,"remaining_time":0.2430313229},
{"learn":[0.8217936922],"iteration":980,"passed_time":11.92055516,"remaining_time":0.230877215},
{"learn":[0.8217551507],"iteration":981,"passed_time":11.93293618,"remaining_time":0.218729991},
{"learn":[0.8217301401],"iteration":982,"passed_time":11.94660953,"remaining_time":0.2066046409},
{"learn":[0.8216940476],"iteration":983,"passed_time":11.96223225,"remaining_time":0.1945078415},
{"learn":[0.8216532977],"iteration":984,"passed_time":11.97649491,"remaining_time":0.1823831712},
{"learn":[0.8215997171],"iteration":985,"passed_time":11.99071053,"remaining_time":0.1702534964},
{"learn":[0.8215713092],"iteration":986,"passed_time":12.00341963,"remaining_time":0.158099752},
{"learn":[0.821547633],"iteration":987,"passed_time":12.01691013,"remaining_time":0.1459543741},
{"learn":[0.8214999423],"iteration":988,"passed_time":12.02824657,"remaining_time":0.1337823177},
{"learn":[0.8214614191],"iteration":989,"passed_time":12.0404859,"remaining_time":0.1216210697},
{"learn":[0.8214331156],"iteration":990,"passed_time":12.05520809,"remaining_time":0.1094822127},
{"learn":[0.821357285],"iteration":991,"passed_time":12.06704921,"remaining_time":0.09731491298},
{"learn":[0.821331889],"iteration":992,"passed_time":12.0805996,"remaining_time":0.08516031946},
{"learn":[0.821295116],"iteration":993,"passed_time":12.08999943,"remaining_time":0.07297786374},
{"learn":[0.8212453915],"iteration":994,"passed_time":12.10365963,"remaining_time":0.06082241019},
{"learn":[0.8212184591],"iteration":995,"passed_time":12.1129389,"remaining_time":0.04864634095},
{"learn":[0.8211883591],"iteration":996,"passed_time":12.12170725,"remaining_time":0.03647454539},
{"learn":[0.8211331786],"iteration":997,"passed_time":12.13235064,"remaining_time":0.02431332794},
{"learn":[0.8210922876],"iteration":998,"passed_time":12.14224845,"remaining_time":0.01215440285},
{"learn":[0.8210421829],"iteration":999,"passed_time":12.15335068,"remaining_time":0}
]}